Workbook

Sheet README
A1: Mortgage delinquency and prepayment model: Excel companion (synthetic data)
A3: Purpose: a live, auditable version of the scorecard, decile, PSI, calibration and scenario calculations for 2,000 out-of-time loans.
A4: All loans are simulated. Nothing here describes real borrowers.
A6: Static values from Python: Scorecard bins, Loan_Sample attributes and Python_Ref, Curves_Python, and the model scalars on Inputs.
A7: Live formulas: Loan_Sample xl_ columns, Score_Calc, Deciles, PSI, Calibration, Scenario and Checks.
A8: Conclusions is static text written at build time.
A10: How to use: change the scenario selector on Inputs (1 to 6) to re-run the shocked PD, expected loss and prepay summary on Scenario.
A11: Change the one-loan calculator inputs on Inputs to score a single loan on Score_Calc (clear a cell to test the missing bin).
A12: Checks cell 'All checks pass' must read 1.
A14: Approximations: the prepay side holds BURNOUT fixed at a value solved to match the Python GBM base prepay (no history in the sample); decile AUC and Gini are trapezoid approximations; the scenario applies the full shock at the snapshot with no ramp.
A15: Python reconciliation is run by mortgage_risk.reconcile_excel against a LibreOffice recalculation; see outputs/excel_reconciliation.json.

Sheet Inputs
A1: Inputs (all typed numbers live here; synthetic data, not real loans)
A3: Scenario selector (1 to 6) | B3: 1 | C3: Matches the scenario table below; change this one cell
A4: LGD assumption | B4: 0.35 | C4: config.LGD_ASSUMPTION
A5: Scorecard PDO (points to double the odds) | B5: 20 | C5: config.SCORECARD_PDO
A6: Scorecard base score | B6: 600 | C6: config.SCORECARD_BASE_SCORE
A7: Scorecard base odds (good:bad) | B7: 50 | C7: config.SCORECARD_BASE_ODDS
A8: Scorecard factor | B8: =Inputs!$B$5/LN(2) -> 28.853901 | C8: PDO / ln 2 (formula)
A9: Scorecard offset | B9: =Inputs!$B$6-Inputs!$B$8*LN(Inputs!$B$7) -> 487.12288 | C9: base score - factor x ln(base odds) (formula)
A10: Scorecard logit intercept | B10: -3.8904456 | C10: Python scorecard fit
A11: PD Platt calibrator slope | B11: 1.0661283 | C11: Python calibrator, applied to the scorecard margin
A12: PD Platt calibrator intercept | B12: 0.2036448 | C12: Python calibrator
A13: Probability clip | B13: 1e-06 | C13: models.PROB_CLIP
A14: Prepay BURNOUT assumption (months) | B14: 36.4 | C14: APPROXIMATION: no burnout history in the sample; one fixed value solved so base 12m prepay matches the Python GBM base
A15: Prepay Platt calibrator slope | B15: 1.1367985 | C15: Python calibrator on the prepay hinge logit
A16: Prepay Platt calibrator intercept | B16: 0.42209988 | C16: Python calibrator
A17: Seasoning ramp months | B17: 30 | C17: SEASONING_RAMP = min(age / this, 1)
A18: Prepay MTM_LTV cap | B18: 120 | C18: models.MTM_LTV_CAP
A19: PSI share floor | B19: 0.0001 | C19: evaluation.PSI_FLOOR
A20: PSI band: stable below | B20: 0.1 | C20: config.PSI_BANDS
A21: PSI band: moderate below | B21: 0.25 | C21: config.PSI_BANDS
A23: Selected scenario | B23: =INDEX($A$29:$A$34,Inputs!$B$3) -> Base
A24: Selected rate shock (bp) | B24: =INDEX($B$29:$B$34,Inputs!$B$3) -> 0
A25: Selected HPI shock (%) | B25: =INDEX($C$29:$C$34,Inputs!$B$3) -> 0
A26: Selected unemployment shock (pt) | B26: =INDEX($D$29:$D$34,Inputs!$B$3) -> 0
A28: Scenario table | B28: rate_bp | C28: hpi_pct | D28: unemp_pt
A29: Base | B29: 0 | C29: 0 | D29: 0
A30: Rates +200bp | B30: 200 | C30: 0 | D30: 0
A31: Rates -200bp | B31: -200 | C31: 0 | D31: 0
A32: HPI -20% | B32: 0 | C32: -20 | D32: 0
A33: Unemployment +4pt | B33: 0 | C33: 0 | D33: 4
A34: Adverse combined | B34: 200 | C34: -20 | D34: 4
A36: Prepay hinge logit term | B36: coef | C36: knot
A37: const | B37: -7.3564132
A38: hinge_0.0 | B38: 2.9007133 | C38: 0
A39: hinge_0.5 | B39: -1.1729917 | C39: 0.5
A40: hinge_1.0 | B40: -2.0790076 | C40: 1
A41: hinge_1.5 | B41: 0.8237186 | C41: 1.5
A42: burnout | B42: -0.033679816
A43: seasoning_ramp | B43: 0.79833974
A44: mtm_ltv | B44: -0.0025470499
A45: fico | B45: 0.0032132194
A47: One-loan calculator inputs (blank = missing) | B47: value
A48: fico | B48: 740
A49: orig_ltv | B49: 80
A50: mtm_ltv | B50: 70
A51: dti | B51: 36
A52: incentive | B52: 0
A53: age | B53: 24
A54: unemp | B54: 4.5
A55: unemp_chg_12m | B55: 0

Sheet Scorecard
A1: Scorecard bin table (inputs from Python; scorecard_table.csv)
A2: Bins are (bin_lo, bin_hi]; the missing bin has blank bounds. Column G is the lookup helper (finite upper edges).
A4: variable | B4: bin_lo | C4: bin_hi | D4: woe | E4: coef | F4: points | G4: edge_helper | I4: variable | J4: coef | K4: best_points | L4: n_bins
A5: fico | B5: -inf | C5: 678 | D5: -1.8822098 | E5: -0.99443831 | F5: 20.915131 | G5: =C5 -> 678 | I5: fico | J5: =E5 -> -0.99443831 | K5: =MAX(F5:F12) -> 137.79311 | L5: 8
A6: fico | B6: 678 | C6: 704 | D6: -0.86967785 | E6: -0.99443831 | F6: 49.96814 | G6: =C6 -> 704 | I6: orig_ltv | J6: =E14 -> -0.65981218 | K6: =MAX(F14:F17) -> 79.656532 | L6: 4
A7: fico | B7: 704 | C7: 713 | D7: -0.51300064 | E7: -0.99443831 | F7: 60.202431 | G7: =C7 -> 713 | I7: mtm_ltv | J7: =E19 -> -0.37555002 | K7: =MAX(F19:F26) -> 81.196161 | L7: 8
A8: fico | B8: 713 | C8: 733 | D8: -0.029042411 | E8: -0.99443831 | F8: 74.08885 | G8: =C8 -> 733 | I8: dti | J8: =E28 -> -1.118789 | K8: =MAX(F28:F35) -> 95.092554 | L8: 8
A9: fico | B9: 733 | C9: 750 | D9: 0.48835816 | E9: -0.99443831 | F9: 88.934844 | G9: =C9 -> 750 | I9: incentive | J9: =E37 -> -0.026412907 | K9: =MAX(F37:F44) -> 75.951471 | L9: 8
A10: fico | B10: 750 | C10: 761 | D10: 0.73318896 | E10: -0.99443831 | F10: 95.959878 | G10: =C10 -> 761 | I10: age | J10: =E46 -> -0.22266667 | K10: =MAX(F46:F52) -> 80.183333 | L10: 7
A11: fico | B11: 761 | C11: 786 | D11: 1.2375038 | E11: -0.99443831 | F11: 110.4304 | G11: =C11 -> 786 | I11: unemp | J11: =E54 -> -0.82079131 | K11: =MAX(F54:F61) -> 86.504374 | L11: 8
A12: fico | B12: 786 | C12: inf | D12: 2.1911271 | E12: -0.99443831 | F12: 137.79311 | I12: unemp_chg_12m | J12: =E63 -> -0.086756991 | K12: =MAX(F63:F68) -> 75.729444 | L12: 6
A13: fico | D13: 0 | E13: -0.99443831 | F13: 74.922176
A14: orig_ltv | B14: -inf | C14: 63.303265 | D14: 0.24867724 | E14: -0.65981218 | F14: 79.656532 | G14: =C14 -> 63.303265
A15: orig_ltv | B15: 63.303265 | C15: 76.784861 | D15: 0.12857965 | E15: -0.65981218 | F15: 77.370095 | G15: =C15 -> 76.784861
A16: orig_ltv | B16: 76.784861 | C16: 87.065598 | D16: 0.050535548 | E16: -0.65981218 | F16: 75.88428 | G16: =C16 -> 87.065598
A17: orig_ltv | B17: 87.065598 | C17: inf | D17: -0.36197087 | E17: -0.65981218 | F17: 68.030918
A18: orig_ltv | D18: 0 | E18: -0.65981218 | F18: 74.922176
A19: mtm_ltv | B19: -inf | C19: 54.611932 | D19: 0.57899015 | E19: -0.37555002 | F19: 81.196161 | G19: =C19 -> 54.611932
A20: mtm_ltv | B20: 54.611932 | C20: 58.116357 | D20: 0.28589934 | E20: -0.37555002 | F20: 78.020205 | G20: =C20 -> 58.116357
A21: mtm_ltv | B21: 58.116357 | C21: 60.504834 | D21: 0.26717933 | E21: -0.37555002 | F21: 77.817353 | G21: =C21 -> 60.504834
A22: mtm_ltv | B22: 60.504834 | C22: 66.17868 | D22: 0.23362161 | E22: -0.37555002 | F22: 77.453719 | G22: =C22 -> 66.17868
A23: mtm_ltv | B23: 66.17868 | C23: 72.017818 | D23: 0.053084309 | E23: -0.37555002 | F23: 75.497402 | G23: =C23 -> 72.017818
A24: mtm_ltv | B24: 72.017818 | C24: 82.264819 | D24: -0.034157851 | E24: -0.37555002 | F24: 74.552039 | G24: =C24 -> 82.264819
A25: mtm_ltv | B25: 82.264819 | C25: 86.876718 | D25: -0.21985597 | E25: -0.37555002 | F25: 72.539798 | G25: =C25 -> 86.876718
A26: mtm_ltv | B26: 86.876718 | C26: inf | D26: -0.82099237 | E26: -0.37555002 | F26: 66.025834
A27: mtm_ltv | D27: 0 | E27: -0.37555002 | F27: 74.922176
A28: dti | B28: -inf | C28: 22 | D28: 0.62482919 | E28: -1.118789 | F28: 95.092554 | G28: =C28 -> 22
A29: dti | B29: 22 | C29: 25 | D29: 0.34921815 | E29: -1.118789 | F29: 86.195436 | G29: =C29 -> 25
A30: dti | B30: 25 | C30: 29 | D30: 0.16509701 | E30: -1.118789 | F30: 80.251743 | G30: =C30 -> 29
A31: dti | B31: 29 | C31: 32 | D31: 0.12691319 | E31: -1.118789 | F31: 79.019115 | G31: =C31 -> 32
A32: dti | B32: 32 | C32: 37 | D32: -0.0008456428 | E32: -1.118789 | F32: 74.894877 | G32: =C32 -> 37
A33: dti | B33: 37 | C33: 41 | D33: -0.13261687 | E33: -1.118789 | F33: 70.641114 | G33: =C33 -> 41
A34: dti | B34: 41 | C34: 45 | D34: -0.30972704 | E34: -1.118789 | F34: 64.923745 | G34: =C34 -> 45
A35: dti | B35: 45 | C35: inf | D35: -0.40068911 | E35: -1.118789 | F35: 61.98736
A36: dti | D36: 0 | E36: -1.118789 | F36: 74.922176
A37: incentive | B37: -inf | C37: -0.54017997 | D37: 1.3505764 | E37: -0.026412907 | F37: 75.951471 | G37: =C37 -> -0.54017997
A38: incentive | B38: -0.54017997 | C38: -0.15653276 | D38: 0.76971683 | E38: -0.026412907 | F38: 75.508789 | G38: =C38 -> -0.15653276
A39: incentive | B39: -0.15653276 | C39: 0.08612299 | D39: 0.33050154 | E39: -0.026412907 | F39: 75.174056 | G39: =C39 -> 0.08612299
A40: incentive | B40: 0.08612299 | C40: 0.2018199 | D40: 0.10218425 | E40: -0.026412907 | F40: 75.000052 | G40: =C40 -> 0.2018199
A41: incentive | B41: 0.2018199 | C41: 0.38705349 | D41: -0.067952013 | E41: -0.026412907 | F41: 74.870389 | G41: =C41 -> 0.38705349
A42: incentive | B42: 0.38705349 | C42: 0.6219461 | D42: -0.27122968 | E42: -0.026412907 | F42: 74.715468 | G42: =C42 -> 0.6219461
A43: incentive | B43: 0.6219461 | C43: 0.89795803 | D43: -0.56945472 | E43: -0.026412907 | F43: 74.488186 | G43: =C43 -> 0.89795803
A44: incentive | B44: 0.89795803 | C44: inf | D44: -0.97550357 | E44: -0.026412907 | F44: 74.17873
A45: incentive | D45: 0 | E45: -0.026412907 | F45: 74.922176
A46: age | B46: -inf | C46: 6 | D46: -0.16153484 | E46: -0.22266667 | F46: 73.884347 | G46: =C46 -> 6
A47: age | B47: 6 | C47: 18 | D47: -0.1142724 | E47: -0.22266667 | F47: 74.187998 | G47: =C47 -> 18
A48: age | B48: 18 | C48: 22 | D48: -0.10877705 | E48: -0.22266667 | F48: 74.223305 | G48: =C48 -> 22
A49: age | B49: 22 | C49: 25 | D49: -0.048559051 | E49: -0.22266667 | F49: 74.610194 | G49: =C49 -> 25
A50: age | B50: 25 | C50: 36 | D50: 0.12386938 | E50: -0.22266667 | F50: 75.718012 | G50: =C50 -> 36
A51: age | B51: 36 | C51: 42 | D51: 0.56987541 | E51: -0.22266667 | F51: 78.583513 | G51: =C51 -> 42
A52: age | B52: 42 | C52: inf | D52: 0.81888237 | E52: -0.22266667 | F52: 80.183333
A53: age | D53: 0 | E53: -0.22266667 | F53: 74.922176
A54: unemp | B54: -inf | C54: 4.4000001 | D54: 0.4890505 | E54: -0.82079131 | F54: 86.504374 | G54: =C54 -> 4.4000001
A55: unemp | B55: 4.4000001 | C55: 4.8000002 | D55: 0.409483 | E55: -0.82079131 | F55: 84.619975 | G55: =C55 -> 4.8000002
A56: unemp | B56: 4.8000002 | C56: 5.1999998 | D56: 0.21442935 | E56: -0.82079131 | F56: 80.000513 | G56: =C56 -> 5.1999998
A57: unemp | B57: 5.1999998 | C57: 5.4749999 | D57: 0.12630355 | E57: -0.82079131 | F57: 77.913427 | G57: =C57 -> 5.4749999
A58: unemp | B58: 5.4749999 | C58: 6.1999998 | D58: 0.015175899 | E58: -0.82079131 | F58: 75.281587 | G58: =C58 -> 6.1999998
A59: unemp | B59: 6.1999998 | C59: 6.5999999 | D59: -0.1198738 | E59: -0.82079131 | F59: 72.083201 | G59: =C59 -> 6.5999999
A60: unemp | B60: 6.5999999 | C60: 7.0999999 | D60: -0.35726487 | E60: -0.82079131 | F60: 66.461061 | G60: =C60 -> 7.0999999
A61: unemp | B61: 7.0999999 | C61: inf | D61: -0.54191718 | E61: -0.82079131 | F61: 62.087935
A62: unemp | D62: 0 | E62: -0.82079131 | F62: 74.922176
A63: unemp_chg_12m | B63: -inf | C63: -0.80000019 | D63: -0.34058219 | E63: -0.086756991 | F63: 74.069604 | G63: =C63 -> -0.80000019
A64: unemp_chg_12m | B64: -0.80000019 | C64: -0.79999971 | D64: -0.28919773 | E64: -0.086756991 | F64: 74.198234 | G64: =C64 -> -0.79999971
A65: unemp_chg_12m | B65: -0.79999971 | C65: -0.67499971 | D65: -0.055077244 | E65: -0.086756991 | F65: 74.784302 | G65: =C65 -> -0.67499971
A66: unemp_chg_12m | B66: -0.67499971 | C66: -0.55000019 | D66: 0.17255905 | E66: -0.086756991 | F66: 75.354139 | G66: =C66 -> -0.55000019
A67: unemp_chg_12m | B67: -0.55000019 | C67: -0.54999971 | D67: 0.19174612 | E67: -0.086756991 | F67: 75.40217 | G67: =C67 -> -0.54999971
A68: unemp_chg_12m | B68: -0.54999971 | C68: inf | D68: 0.32248451 | E68: -0.086756991 | F68: 75.729444
A69: unemp_chg_12m | D69: 0 | E69: -0.086756991 | F69: 74.922176

Sheet Score_Calc
A1: One-loan scorecard calculator (inputs are on the Inputs sheet; blank input = missing bin)
A5: variable | B5: value | C5: bin_number | D5: woe | E5: coef | F5: coef x woe | G5: points | H5: best_bin_points | I5: shortfall | J5: tiebreak_key
A6: fico | B6: =IF(ISBLANK(Inputs!$B$48),"",Inputs!$B$48) -> 740 | C6: =IF(ISNUMBER(B6),SUMPRODUCT(--(Scorecard!$G$5:$G$11<B6))+1,"missing") -> 5 | D6: =IF(ISNUMBER(C6),INDEX(Scorecard!$D$5:$D$12,C6),Scorecard!$D$13) -> 0.48835816 | E6: =Scorecard!$J$5 -> -0.99443831 | F6: =D6*E6 -> -0.48564206 | G6: =IF(ISNUMBER(C6),INDEX(Scorecard!$F$5:$F$12,C6),Scorecard!$F$13) -> 88.934844 | H6: =Scorecard!$K$5 -> 137.79311 | I6: =H6-G6 -> 48.858271 | J6: =I6-ROW()*0.000000001 -> 48.858271
A7: orig_ltv | B7: =IF(ISBLANK(Inputs!$B$49),"",Inputs!$B$49) -> 80 | C7: =IF(ISNUMBER(B7),SUMPRODUCT(--(Scorecard!$G$14:$G$16<B7))+1,"missing") -> 3 | D7: =IF(ISNUMBER(C7),INDEX(Scorecard!$D$14:$D$17,C7),Scorecard!$D$18) -> 0.050535548 | E7: =Scorecard!$J$6 -> -0.65981218 | F7: =D7*E7 -> -0.03334397 | G7: =IF(ISNUMBER(C7),INDEX(Scorecard!$F$14:$F$17,C7),Scorecard!$F$18) -> 75.88428 | H7: =Scorecard!$K$6 -> 79.656532 | I7: =H7-G7 -> 3.7722523 | J7: =I7-ROW()*0.000000001 -> 3.7722523
A8: mtm_ltv | B8: =IF(ISBLANK(Inputs!$B$50),"",Inputs!$B$50) -> 70 | C8: =IF(ISNUMBER(B8),SUMPRODUCT(--(Scorecard!$G$19:$G$25<B8))+1,"missing") -> 5 | D8: =IF(ISNUMBER(C8),INDEX(Scorecard!$D$19:$D$26,C8),Scorecard!$D$27) -> 0.053084309 | E8: =Scorecard!$J$7 -> -0.37555002 | F8: =D8*E8 -> -0.019935813 | G8: =IF(ISNUMBER(C8),INDEX(Scorecard!$F$19:$F$26,C8),Scorecard!$F$27) -> 75.497402 | H8: =Scorecard!$K$7 -> 81.196161 | I8: =H8-G8 -> 5.6987594 | J8: =I8-ROW()*0.000000001 -> 5.6987594
A9: dti | B9: =IF(ISBLANK(Inputs!$B$51),"",Inputs!$B$51) -> 36 | C9: =IF(ISNUMBER(B9),SUMPRODUCT(--(Scorecard!$G$28:$G$34<B9))+1,"missing") -> 5 | D9: =IF(ISNUMBER(C9),INDEX(Scorecard!$D$28:$D$35,C9),Scorecard!$D$36) -> -0.0008456428 | E9: =Scorecard!$J$8 -> -1.118789 | F9: =D9*E9 -> 0.00094609587 | G9: =IF(ISNUMBER(C9),INDEX(Scorecard!$F$28:$F$35,C9),Scorecard!$F$36) -> 74.894877 | H9: =Scorecard!$K$8 -> 95.092554 | I9: =H9-G9 -> 20.197677 | J9: =I9-ROW()*0.000000001 -> 20.197677
A10: incentive | B10: =IF(ISBLANK(Inputs!$B$52),"",Inputs!$B$52) -> 0 | C10: =IF(ISNUMBER(B10),SUMPRODUCT(--(Scorecard!$G$37:$G$43<B10))+1,"missing") -> 3 | D10: =IF(ISNUMBER(C10),INDEX(Scorecard!$D$37:$D$44,C10),Scorecard!$D$45) -> 0.33050154 | E10: =Scorecard!$J$9 -> -0.026412907 | F10: =D10*E10 -> -0.0087295064 | G10: =IF(ISNUMBER(C10),INDEX(Scorecard!$F$37:$F$44,C10),Scorecard!$F$45) -> 75.174056 | H10: =Scorecard!$K$9 -> 75.951471 | I10: =H10-G10 -> 0.77741471 | J10: =I10-ROW()*0.000000001 -> 0.7774147
A11: age | B11: =IF(ISBLANK(Inputs!$B$53),"",Inputs!$B$53) -> 24 | C11: =IF(ISNUMBER(B11),SUMPRODUCT(--(Scorecard!$G$46:$G$51<B11))+1,"missing") -> 4 | D11: =IF(ISNUMBER(C11),INDEX(Scorecard!$D$46:$D$52,C11),Scorecard!$D$53) -> -0.048559051 | E11: =Scorecard!$J$10 -> -0.22266667 | F11: =D11*E11 -> 0.010812482 | G11: =IF(ISNUMBER(C11),INDEX(Scorecard!$F$46:$F$52,C11),Scorecard!$F$53) -> 74.610194 | H11: =Scorecard!$K$10 -> 80.183333 | I11: =H11-G11 -> 5.5731394 | J11: =I11-ROW()*0.000000001 -> 5.5731394
A12: unemp | B12: =IF(ISBLANK(Inputs!$B$54),"",Inputs!$B$54) -> 4.5 | C12: =IF(ISNUMBER(B12),SUMPRODUCT(--(Scorecard!$G$54:$G$60<B12))+1,"missing") -> 2 | D12: =IF(ISNUMBER(C12),INDEX(Scorecard!$D$54:$D$61,C12),Scorecard!$D$62) -> 0.409483 | E12: =Scorecard!$J$11 -> -0.82079131 | F12: =D12*E12 -> -0.33610009 | G12: =IF(ISNUMBER(C12),INDEX(Scorecard!$F$54:$F$61,C12),Scorecard!$F$62) -> 84.619975 | H12: =Scorecard!$K$11 -> 86.504374 | I12: =H12-G12 -> 1.8843995 | J12: =I12-ROW()*0.000000001 -> 1.8843995
A13: unemp_chg_12m | B13: =IF(ISBLANK(Inputs!$B$55),"",Inputs!$B$55) -> 0 | C13: =IF(ISNUMBER(B13),SUMPRODUCT(--(Scorecard!$G$63:$G$67<B13))+1,"missing") -> 6 | D13: =IF(ISNUMBER(C13),INDEX(Scorecard!$D$63:$D$68,C13),Scorecard!$D$69) -> 0.32248451 | E13: =Scorecard!$J$12 -> -0.086756991 | F13: =D13*E13 -> -0.027977786 | G13: =IF(ISNUMBER(C13),INDEX(Scorecard!$F$63:$F$68,C13),Scorecard!$F$69) -> 75.729444 | H13: =Scorecard!$K$12 -> 75.729444 | I13: =H13-G13 -> 0 | J13: =I13-ROW()*0.000000001 -> -1.3e-08
A15: Sum of coef x woe | B15: =SUM(F6:F13) -> -0.89997065
A16: Logit margin | B16: =Inputs!$B$10+B15 -> -4.7904162
A17: PD (calibrated) | B17: =MIN(1-Inputs!$B$13,MAX(Inputs!$B$13,1/(1+EXP(-(Inputs!$B$11*B16+Inputs!$B$12))))) -> 0.0073655155
A18: Total score | B18: =Inputs!$B$9-Inputs!$B$8*B16 -> 625.34507
A19: Sum of per-variable points (equals total score) | B19: =SUM(G6:G13) -> 625.34507
A21: Top 3 variables by points shortfall versus the best bin
A22: rank | B22: variable | C22: shortfall_points
A23: =ROW()-22 -> 1 | B23: =INDEX($A$6:$A$13,MATCH(LARGE($J$6:$J$13,A23),$J$6:$J$13,0)) -> fico | C23: =INDEX($I$6:$I$13,MATCH(LARGE($J$6:$J$13,A23),$J$6:$J$13,0)) -> 48.858271
A24: =ROW()-22 -> 2 | B24: =INDEX($A$6:$A$13,MATCH(LARGE($J$6:$J$13,A24),$J$6:$J$13,0)) -> dti | C24: =INDEX($I$6:$I$13,MATCH(LARGE($J$6:$J$13,A24),$J$6:$J$13,0)) -> 20.197677
A25: =ROW()-22 -> 3 | B25: =INDEX($A$6:$A$13,MATCH(LARGE($J$6:$J$13,A25),$J$6:$J$13,0)) -> mtm_ltv | C25: =INDEX($I$6:$I$13,MATCH(LARGE($J$6:$J$13,A25),$J$6:$J$13,0)) -> 5.6987594

Sheet Loan_Sample
A1: Loan sample: 2,000 out-of-time snapshot loans (synthetic). Python columns are static; xl_ columns are live formulas.
A2: Attributes were scored in float32 in Python, so they are stored at float32 precision to land on the same bins.
A4: loan_id | B4: snapshot_date | C4: fico | D4: orig_ltv | E4: mtm_ltv | F4: dti | G4: orig_rate | H4: incentive | I4: age | J4: log_upb | K4: unemp | L4: unemp_chg_12m | M4: hpi_chg_12m | N4: times_30dpd_12m | O4: dlq_status | P4: purpose | Q4: occupancy | R4: n_borrowers | S4: state | T4: target_pd12 | U4: cur_upb | V4: py_scorecard_pd | W4: py_scorecard_points | X4: py_gbm_pd | Y4: xl_woe_fico | Z4: xl_woe_orig_ltv | AA4: xl_woe_mtm_ltv | AB4: xl_woe_dti | AC4: xl_woe_incentive | AD4: xl_woe_age | AE4: xl_woe_unemp | AF4: xl_woe_unemp_chg_12m | AG4: xl_margin | AH4: xl_pd | AI4: xl_points | AJ4: xl_rank | AK4: xl_decile
A5: 53 | B5: 2021-07-31 | C5: 770 | D5: 88.366867 | E5: 84.254295 | F5: 37 | G5: 3.1359999 | H5: 0.11933327 | I5: 12 | J5: 12.364779 | K5: 5.4333334 | L5: -3.5 | M5: 2.7406642 | N5: 0 | O5: 0 | P5: C | Q5: O | R5: 2 | S5: GA | T5: 1 | U5: 234398.6 | V5: 0.00691461 | W5: 627.06708 | X5: 0.0096103121 | Y5: =IF(ISNUMBER(C5),INDEX(Scorecard!$D$5:$D$12,SUMPRODUCT(--(Scorecard!$G$5:$G$11<C5))+1),Scorecard!$D$13) -> 1.2375038 | Z5: =IF(ISNUMBER(D5),INDEX(Scorecard!$D$14:$D$17,SUMPRODUCT(--(Scorecard!$G$14:$G$16<D5))+1),Scorecard!$D$18) -> -0.36197087 | AA5: =IF(ISNUMBER(E5),INDEX(Scorecard!$D$19:$D$26,SUMPRODUCT(--(Scorecard!$G$19:$G$25<E5))+1),Scorecard!$D$27) -> -0.21985597 | AB5: =IF(ISNUMBER(F5),INDEX(Scorecard!$D$28:$D$35,SUMPRODUCT(--(Scorecard!$G$28:$G$34<F5))+1),Scorecard!$D$36) -> -0.0008456428 | AC5: =IF(ISNUMBER(H5),INDEX(Scorecard!$D$37:$D$44,SUMPRODUCT(--(Scorecard!$G$37:$G$43<H5))+1),Scorecard!$D$45) -> 0.10218425 | AD5: =IF(ISNUMBER(I5),INDEX(Scorecard!$D$46:$D$52,SUMPRODUCT(--(Scorecard!$G$46:$G$51<I5))+1),Scorecard!$D$53) -> -0.1142724 | AE5: =IF(ISNUMBER(K5),INDEX(Scorecard!$D$54:$D$61,SUMPRODUCT(--(Scorecard!$G$54:$G$60<K5))+1),Scorecard!$D$62) -> 0.12630355 | AF5: =IF(ISNUMBER(L5),INDEX(Scorecard!$D$63:$D$68,SUMPRODUCT(--(Scorecard!$G$63:$G$67<L5))+1),Scorecard!$D$69) -> -0.34058219 | AG5: =Inputs!$B$10+Scorecard!$J$5*Y5+Scorecard!$J$6*Z5+Scorecard!$J$7*AA5+Scorecard!$J$8*AB5+Scorecard!$J$9*AC5+Scorecard!$J$10*AD5+Scorecard!$J$11*AE5+Scorecard!$J$12*AF5 -> -4.8500963 | AH5: =MIN(1-Inputs!$B$13,MAX(Inputs!$B$13,1/(1+EXP(-(Inputs!$B$11*AG5+Inputs!$B$12))))) -> 0.00691461 | AI5: =Inputs!$B$9-Inputs!$B$8*AG5 -> 627.06707 | AJ5: =RANK(AH5,$AH$5:$AH$2004,0)+COUNTIF($AH$4:AH4,AH5) -> 1062 | AK5: =IF(AJ5<=Deciles!$B$5*(Deciles!$B$4+1),INT((AJ5-1)/(Deciles!$B$4+1))+1,Deciles!$B$5+INT((AJ5-1-Deciles!$B$5*(Deciles!$B$4+1))/Deciles!$B$4)+1) -> 6
A6: 60 | B6: 2020-07-31 | C6: 736 | D6: 90.132195 | E6: 82.01059 | F6: 43 | G6: 4.4029999 | H6: 1.1696665 | I6: 23 | J6: 12.713851 | K6: 8.9333334 | L6: 5.071795 | M6: 1.950057 | N6: 0 | O6: 0 | P6: P | Q6: O | R6: 2 | S6: GA | T6: 0 | U6: 332319.2 | V6: 0.034200855 | W6: 583.04785 | X6: 0.029188776 | Y6: =IF(ISNUMBER(C6),INDEX(Scorecard!$D$5:$D$12,SUMPRODUCT(--(Scorecard!$G$5:$G$11<C6))+1),Scorecard!$D$13) -> 0.48835816 | Z6: =IF(ISNUMBER(D6),INDEX(Scorecard!$D$14:$D$17,SUMPRODUCT(--(Scorecard!$G$14:$G$16<D6))+1),Scorecard!$D$18) -> -0.36197087 | AA6: =IF(ISNUMBER(E6),INDEX(Scorecard!$D$19:$D$26,SUMPRODUCT(--(Scorecard!$G$19:$G$25<E6))+1),Scorecard!$D$27) -> -0.034157851 | AB6: =IF(ISNUMBER(F6),INDEX(Scorecard!$D$28:$D$35,SUMPRODUCT(--(Scorecard!$G$28:$G$34<F6))+1),Scorecard!$D$36) -> -0.30972704 | AC6: =IF(ISNUMBER(H6),INDEX(Scorecard!$D$37:$D$44,SUMPRODUCT(--(Scorecard!$G$37:$G$43<H6))+1),Scorecard!$D$45) -> -0.97550357 | AD6: =IF(ISNUMBER(I6),INDEX(Scorecard!$D$46:$D$52,SUMPRODUCT(--(Scorecard!$G$46:$G$51<I6))+1),Scorecard!$D$53) -> -0.048559051 | AE6: =IF(ISNUMBER(K6),INDEX(Scorecard!$D$54:$D$61,SUMPRODUCT(--(Scorecard!$G$54:$G$60<K6))+1),Scorecard!$D$62) -> -0.54191718 | AF6: =IF(ISNUMBER(L6),INDEX(Scorecard!$D$63:$D$68,SUMPRODUCT(--(Scorecard!$G$63:$G$67<L6))+1),Scorecard!$D$69) -> 0.32248451 | AG6: =Inputs!$B$10+Scorecard!$J$5*Y6+Scorecard!$J$6*Z6+Scorecard!$J$7*AA6+Scorecard!$J$8*AB6+Scorecard!$J$9*AC6+Scorecard!$J$10*AD6+Scorecard!$J$11*AE6+Scorecard!$J$12*AF6 -> -3.3245062 | AH6: =MIN(1-Inputs!$B$13,MAX(Inputs!$B$13,1/(1+EXP(-(Inputs!$B$11*AG6+Inputs!$B$12))))) -> 0.034200854 | AI6: =Inputs!$B$9-Inputs!$B$8*AG6 -> 583.04785 | AJ6: =RANK(AH6,$AH$5:$AH$2004,0)+COUNTIF($AH$4:AH5,AH6) -> 263 | AK6: =IF(AJ6<=Deciles!$B$5*(Deciles!$B$4+1),INT((AJ6-1)/(Deciles!$B$4+1))+1,Deciles!$B$5+INT((AJ6-1-Deciles!$B$5*(Deciles!$B$4+1))/Deciles!$B$4)+1) -> 2
A7: 90 | B7: 2022-01-31 | C7: 700 | D7: 80 | E7: 46.712036 | F7: 27 | G7: 4.7350001 | H7: 1.2183335 | I7: 105 | J7: 11.751288 | K7: 4.1583333 | L7: -1.875 | M7: 4.7441649 | N7: 0 | O7: 0 | P7: N | Q7: O | R7: 2 | S7: TX | T7: 0 | U7: 126916.92 | V7: 0.017128991 | W7: 602.23639 | X7: 0.015653349 | Y7: =IF(ISNUMBER(C7),INDEX(Scorecard!$D$5:$D$12,SUMPRODUCT(--(Scorecard!$G$5:$G$11<C7))+1),Scorecard!$D$13) -> -0.86967785 | Z7: =IF(ISNUMBER(D7),INDEX(Scorecard!$D$14:$D$17,SUMPRODUCT(--(Scorecard!$G$14:$G$16<D7))+1),Scorecard!$D$18) -> 0.050535548 | AA7: =IF(ISNUMBER(E7),INDEX(Scorecard!$D$19:$D$26,SUMPRODUCT(--(Scorecard!$G$19:$G$25<E7))+1),Scorecard!$D$27) -> 0.57899015 | AB7: =IF(ISNUMBER(F7),INDEX(Scorecard!$D$28:$D$35,SUMPRODUCT(--(Scorecard!$G$28:$G$34<F7))+1),Scorecard!$D$36) -> 0.16509701 | AC7: =IF(ISNUMBER(H7),INDEX(Scorecard!$D$37:$D$44,SUMPRODUCT(--(Scorecard!$G$37:$G$43<H7))+1),Scorecard!$D$45) -> -0.97550357 | AD7: =IF(ISNUMBER(I7),INDEX(Scorecard!$D$46:$D$52,SUMPRODUCT(--(Scorecard!$G$46:$G$51<I7))+1),Scorecard!$D$53) -> 0.81888237 | AE7: =IF(ISNUMBER(K7),INDEX(Scorecard!$D$54:$D$61,SUMPRODUCT(--(Scorecard!$G$54:$G$60<K7))+1),Scorecard!$D$62) -> 0.4890505 | AF7: =IF(ISNUMBER(L7),INDEX(Scorecard!$D$63:$D$68,SUMPRODUCT(--(Scorecard!$G$63:$G$67<L7))+1),Scorecard!$D$69) -> -0.34058219 | AG7: =Inputs!$B$10+Scorecard!$J$5*Y7+Scorecard!$J$6*Z7+Scorecard!$J$7*AA7+Scorecard!$J$8*AB7+Scorecard!$J$9*AC7+Scorecard!$J$10*AD7+Scorecard!$J$11*AE7+Scorecard!$J$12*AF7 -> -3.9895295 | AH7: =MIN(1-Inputs!$B$13,MAX(Inputs!$B$13,1/(1+EXP(-(Inputs!$B$11*AG7+Inputs!$B$12))))) -> 0.017128991 | AI7: =Inputs!$B$9-Inputs!$B$8*AG7 -> 602.23637 | AJ7: =RANK(AH7,$AH$5:$AH$2004,0)+COUNTIF($AH$4:AH6,AH7) -> 522 | AK7: =IF(AJ7<=Deciles!$B$5*(Deciles!$B$4+1),INT((AJ7-1)/(Deciles!$B$4+1))+1,Deciles!$B$5+INT((AJ7-1-Deciles!$B$5*(Deciles!$B$4+1))/Deciles!$B$4)+1) -> 3
A8: 234 | B8: 2022-01-31 | C8: 786 | D8: 80 | E8: 77.960373 | F8: 23 | G8: 3.0780001 | H8: -0.43866658 | I8: 5 | J8: 11.92403 | K8: 4.4583335 | L8: -1.875 | M8: 4.2343502 | N8: 0 | O8: 0 | P8: P | Q8: O | R8: 2 | S8: PA | T8: 0 | U8: 150848.31 | V8: 0.002461225 | W8: 655.1449 | X8: 0.0021670756 | Y8: =IF(ISNUMBER(C8),INDEX(Scorecard!$D$5:$D$12,SUMPRODUCT(--(Scorecard!$G$5:$G$11<C8))+1),Scorecard!$D$13) -> 1.2375038 | Z8: =IF(ISNUMBER(D8),INDEX(Scorecard!$D$14:$D$17,SUMPRODUCT(--(Scorecard!$G$14:$G$16<D8))+1),Scorecard!$D$18) -> 0.050535548 | AA8: =IF(ISNUMBER(E8),INDEX(Scorecard!$D$19:$D$26,SUMPRODUCT(--(Scorecard!$G$19:$G$25<E8))+1),Scorecard!$D$27) -> -0.034157851 | AB8: =IF(ISNUMBER(F8),INDEX(Scorecard!$D$28:$D$35,SUMPRODUCT(--(Scorecard!$G$28:$G$34<F8))+1),Scorecard!$D$36) -> 0.34921815 | AC8: =IF(ISNUMBER(H8),INDEX(Scorecard!$D$37:$D$44,SUMPRODUCT(--(Scorecard!$G$37:$G$43<H8))+1),Scorecard!$D$45) -> 0.76971683 | AD8: =IF(ISNUMBER(I8),INDEX(Scorecard!$D$46:$D$52,SUMPRODUCT(--(Scorecard!$G$46:$G$51<I8))+1),Scorecard!$D$53) -> -0.16153484 | AE8: =IF(ISNUMBER(K8),INDEX(Scorecard!$D$54:$D$61,SUMPRODUCT(--(Scorecard!$G$54:$G$60<K8))+1),Scorecard!$D$62) -> 0.409483 | AF8: =IF(ISNUMBER(L8),INDEX(Scorecard!$D$63:$D$68,SUMPRODUCT(--(Scorecard!$G$63:$G$67<L8))+1),Scorecard!$D$69) -> -0.34058219 | AG8: =Inputs!$B$10+Scorecard!$J$5*Y8+Scorecard!$J$6*Z8+Scorecard!$J$7*AA8+Scorecard!$J$8*AB8+Scorecard!$J$9*AC8+Scorecard!$J$10*AD8+Scorecard!$J$11*AE8+Scorecard!$J$12*AF8 -> -5.8231985 | AH8: =MIN(1-Inputs!$B$13,MAX(Inputs!$B$13,1/(1+EXP(-(Inputs!$B$11*AG8+Inputs!$B$12))))) -> 0.002461225 | AI8: =Inputs!$B$9-Inputs!$B$8*AG8 -> 655.14487 | AJ8: =RANK(AH8,$AH$5:$AH$2004,0)+COUNTIF($AH$4:AH7,AH8) -> 1630 | AK8: =IF(AJ8<=Deciles!$B$5*(Deciles!$B$4+1),INT((AJ8-1)/(Deciles!$B$4+1))+1,Deciles!$B$5+INT((AJ8-1-Deciles!$B$5*(Deciles!$B$4+1))/Deciles!$B$4)+1) -> 9
A9: 268 | B9: 2020-07-31 | C9: 731 | D9: 80 | E9: 79.192024 | F9: 50 | G9: 4.0489998 | H9: 0.81566644 | I9: 7 | J9: 11.961211 | K9: 9.6333332 | L9: 5.0717945 | M9: 2.5737188 | N9: 0 | O9: 0 | P9: P | Q9: O | R9: 2 | S9: CA | T9: 0 | U9: 156562.62 | V9: 0.048815023 | W9: 573.0061 | X9: 0.051605243 | Y9: =IF(ISNUMBER(C9),INDEX(Scorecard!$D$5:$D$12,SUMPRODUCT(--(Scorecard!$G$5:$G$11<C9))+1),Scorecard!$D$13) -> -0.029042411 | Z9: =IF(ISNUMBER(D9),INDEX(Scorecard!$D$14:$D$17,SUMPRODUCT(--(Scorecard!$G$14:$G$16<D9))+1),Scorecard!$D$18) -> 0.050535548 | AA9: =IF(ISNUMBER(E9),INDEX(Scorecard!$D$19:$D$26,SUMPRODUCT(--(Scorecard!$G$19:$G$25<E9))+1),Scorecard!$D$27) -> -0.034157851 | AB9: =IF(ISNUMBER(F9),INDEX(Scorecard!$D$28:$D$35,SUMPRODUCT(--(Scorecard!$G$28:$G$34<F9))+1),Scorecard!$D$36) -> -0.40068911 | AC9: =IF(ISNUMBER(H9),INDEX(Scorecard!$D$37:$D$44,SUMPRODUCT(--(Scorecard!$G$37:$G$43<H9))+1),Scorecard!$D$45) -> -0.56945472 | AD9: =IF(ISNUMBER(I9),INDEX(Scorecard!$D$46:$D$52,SUMPRODUCT(--(Scorecard!$G$46:$G$51<I9))+1),Scorecard!$D$53) -> -0.1142724 | AE9: =IF(ISNUMBER(K9),INDEX(Scorecard!$D$54:$D$61,SUMPRODUCT(--(Scorecard!$G$54:$G$60<K9))+1),Scorecard!$D$62) -> -0.54191718 | AF9: =IF(ISNUMBER(L9),INDEX(Scorecard!$D$63:$D$68,SUMPRODUCT(--(Scorecard!$G$63:$G$67<L9))+1),Scorecard!$D$69) -> 0.32248451 | AG9: =Inputs!$B$10+Scorecard!$J$5*Y9+Scorecard!$J$6*Z9+Scorecard!$J$7*AA9+Scorecard!$J$8*AB9+Scorecard!$J$9*AC9+Scorecard!$J$10*AD9+Scorecard!$J$11*AE9+Scorecard!$J$12*AF9 -> -2.9764854 | AH9: =MIN(1-Inputs!$B$13,MAX(Inputs!$B$13,1/(1+EXP(-(Inputs!$B$11*AG9+Inputs!$B$12))))) -> 0.048815021 | AI9: =Inputs!$B$9-Inputs!$B$8*AG9 -> 573.00609 | AJ9: =RANK(AH9,$AH$5:$AH$2004,0)+COUNTIF($AH$4:AH8,AH9) -> 151 | AK9: =IF(AJ9<=Deciles!$B$5*(Deciles!$B$4+1),INT((AJ9-1)/(Deciles!$B$4+1))+1,Deciles!$B$5+INT((AJ9-1-Deciles!$B$5*(Deciles!$B$4+1))/Deciles!$B$4)+1) -> 1
A10: 273 | B10: 2023-07-31 | C10: 642 | D10: 80 | E10: 64.415588 | F10: 29 | G10: 3.6489999 | H10: -2.9843333 | I10: 32 | J10: 12.226515 | K10: 4.4000001 | L10: -0.20833302 | M10: 6.5481968 | N10: 0 | O10: 0 | P10: P | Q10: O | R10: 1 | S10: AZ | T10: 0 | U10: 204130.56 | V10: 0.057335999 | W10: 568.4082 | X10: 0.084425569 | Y10: =IF(ISNUMBER(C10),INDEX(Scorecard!$D$5:$D$12,SUMPRODUCT(--(Scorecard!$G$5:$G$11<C10))+1),Scorecard!$D$13) -> -1.8822098 | Z10: =IF(ISNUMBER(D10),INDEX(Scorecard!$D$14:$D$17,SUMPRODUCT(--(Scorecard!$G$14:$G$16<D10))+1),Scorecard!$D$18) -> 0.050535548 | AA10: =IF(ISNUMBER(E10),INDEX(Scorecard!$D$19:$D$26,SUMPRODUCT(--(Scorecard!$G$19:$G$25<E10))+1),Scorecard!$D$27) -> 0.23362161 | AB10: =IF(ISNUMBER(F10),INDEX(Scorecard!$D$28:$D$35,SUMPRODUCT(--(Scorecard!$G$28:$G$34<F10))+1),Scorecard!$D$36) -> 0.16509701 | AC10: =IF(ISNUMBER(H10),INDEX(Scorecard!$D$37:$D$44,SUMPRODUCT(--(Scorecard!$G$37:$G$43<H10))+1),Scorecard!$D$45) -> 1.3505764 | AD10: =IF(ISNUMBER(I10),INDEX(Scorecard!$D$46:$D$52,SUMPRODUCT(--(Scorecard!$G$46:$G$51<I10))+1),Scorecard!$D$53) -> 0.12386938 | AE10: =IF(ISNUMBER(K10),INDEX(Scorecard!$D$54:$D$61,SUMPRODUCT(--(Scorecard!$G$54:$G$60<K10))+1),Scorecard!$D$62) -> 0.4890505 | AF10: =IF(ISNUMBER(L10),INDEX(Scorecard!$D$63:$D$68,SUMPRODUCT(--(Scorecard!$G$63:$G$67<L10))+1),Scorecard!$D$69) -> 0.32248451 | AG10: =Inputs!$B$10+Scorecard!$J$5*Y10+Scorecard!$J$6*Z10+Scorecard!$J$7*AA10+Scorecard!$J$8*AB10+Scorecard!$J$9*AC10+Scorecard!$J$10*AD10+Scorecard!$J$11*AE10+Scorecard!$J$12*AF10 -> -2.8171338 | AH10: =MIN(1-Inputs!$B$13,MAX(Inputs!$B$13,1/(1+EXP(-(Inputs!$B$11*AG10+Inputs!$B$12))))) -> 0.057336 | AI10: =Inputs!$B$9-Inputs!$B$8*AG10 -> 568.40817 | AJ10: =RANK(AH10,$AH$5:$AH$2004,0)+COUNTIF($AH$4:AH9,AH10) -> 122 | AK10: =IF(AJ10<=Deciles!$B$5*(Deciles!$B$4+1),INT((AJ10-1)/(Deciles!$B$4+1))+1,Deciles!$B$5+INT((AJ10-1-Deciles!$B$5*(Deciles!$B$4+1))/Deciles!$B$4)+1) -> 1
A11: 304 | B11: 2023-07-31 | C11: 749 | D11: 80 | E11: 44.414982 | F11: 26 | G11: 3.8599999 | H11: -2.7733333 | I11: 109 | J11: 12.1935 | K11: 3.7 | L11: -0.20833325 | M11: 4.7441678 | N11: 0 | O11: 0 | P11: N | Q11: O | R11: 2 | S11: TX | T11: 0 | U11: 197501.1 | V11: 0.0036248001 | W11: 644.63562 | X11: 0.0017800222 | Y11: =IF(ISNUMBER(C11),INDEX(Scorecard!$D$5:$D$12,SUMPRODUCT(--(Scorecard!$G$5:$G$11<C11))+1),Scorecard!$D$13) -> 0.48835816 | Z11: =IF(ISNUMBER(D11),INDEX(Scorecard!$D$14:$D$17,SUMPRODUCT(--(Scorecard!$G$14:$G$16<D11))+1),Scorecard!$D$18) -> 0.050535548 | AA11: =IF(ISNUMBER(E11),INDEX(Scorecard!$D$19:$D$26,SUMPRODUCT(--(Scorecard!$G$19:$G$25<E11))+1),Scorecard!$D$27) -> 0.57899015 | AB11: =IF(ISNUMBER(F11),INDEX(Scorecard!$D$28:$D$35,SUMPRODUCT(--(Scorecard!$G$28:$G$34<F11))+1),Scorecard!$D$36) -> 0.16509701 | AC11: =IF(ISNUMBER(H11),INDEX(Scorecard!$D$37:$D$44,SUMPRODUCT(--(Scorecard!$G$37:$G$43<H11))+1),Scorecard!$D$45) -> 1.3505764 | AD11: =IF(ISNUMBER(I11),INDEX(Scorecard!$D$46:$D$52,SUMPRODUCT(--(Scorecard!$G$46:$G$51<I11))+1),Scorecard!$D$53) -> 0.81888237 | AE11: =IF(ISNUMBER(K11),INDEX(Scorecard!$D$54:$D$61,SUMPRODUCT(--(Scorecard!$G$54:$G$60<K11))+1),Scorecard!$D$62) -> 0.4890505 | AF11: =IF(ISNUMBER(L11),INDEX(Scorecard!$D$63:$D$68,SUMPRODUCT(--(Scorecard!$G$63:$G$67<L11))+1),Scorecard!$D$69) -> 0.32248451 | AG11: =Inputs!$B$10+Scorecard!$J$5*Y11+Scorecard!$J$6*Z11+Scorecard!$J$7*AA11+Scorecard!$J$8*AB11+Scorecard!$J$9*AC11+Scorecard!$J$10*AD11+Scorecard!$J$11*AE11+Scorecard!$J$12*AF11 -> -5.4589768 | AH11: =MIN(1-Inputs!$B$13,MAX(Inputs!$B$13,1/(1+EXP(-(Inputs!$B$11*AG11+Inputs!$B$12))))) -> 0.0036248001 | AI11: =Inputs!$B$9-Inputs!$B$8*AG11 -> 644.63565 | AJ11: =RANK(AH11,$AH$5:$AH$2004,0)+COUNTIF($AH$4:AH10,AH11) -> 1443 | AK11: =IF(AJ11<=Deciles!$B$5*(Deciles!$B$4+1),INT((AJ11-1)/(Deciles!$B$4+1))+1,Deciles!$B$5+INT((AJ11-1-Deciles!$B$5*(Deciles!$B$4+1))/Deciles!$B$4)+1) -> 8
A12: 337 | B12: 2023-01-31 | C12: 816 | D12: 64.000336 | E12: 50.710003 | F12: 33 | G12: 3.6159999 | H12: -2.8173335 | I12: 40 | J12: 11.798711 | K12: 5.1999998 | L12: -0.45833349 | M12: 7.3308272 | N12: 0 | O12: 0 | P12: P | Q12: I | R12: 2 | S12: NV | T12: 0 | U12: 133080.64 | V12: 0.0009302359 | W12: 681.51917 | X12: 0.00062655413 | Y12: =IF(ISNUMBER(C12),INDEX(Scorecard!$D$5:$D$12,SUMPRODUCT(--(Scorecard!$G$5:$G$11<C12))+1),Scorecard!$D$13) -> 2.1911271 | Z12: =IF(ISNUMBER(D12),INDEX(Scorecard!$D$14:$D$17,SUMPRODUCT(--(Scorecard!$G$14:$G$16<D12))+1),Scorecard!$D$18) -> 0.12857965 | AA12: =IF(ISNUMBER(E12),INDEX(Scorecard!$D$19:$D$26,SUMPRODUCT(--(Scorecard!$G$19:$G$25<E12))+1),Scorecard!$D$27) -> 0.57899015 | AB12: =IF(ISNUMBER(F12),INDEX(Scorecard!$D$28:$D$35,SUMPRODUCT(--(Scorecard!$G$28:$G$34<F12))+1),Scorecard!$D$36) -> -0.0008456428 | AC12: =IF(ISNUMBER(H12),INDEX(Scorecard!$D$37:$D$44,SUMPRODUCT(--(Scorecard!$G$37:$G$43<H12))+1),Scorecard!$D$45) -> 1.3505764 | AD12: =IF(ISNUMBER(I12),INDEX(Scorecard!$D$46:$D$52,SUMPRODUCT(--(Scorecard!$G$46:$G$51<I12))+1),Scorecard!$D$53) -> 0.56987541 | AE12: =IF(ISNUMBER(K12),INDEX(Scorecard!$D$54:$D$61,SUMPRODUCT(--(Scorecard!$G$54:$G$60<K12))+1),Scorecard!$D$62) -> 0.21442935 | AF12: =IF(ISNUMBER(L12),INDEX(Scorecard!$D$63:$D$68,SUMPRODUCT(--(Scorecard!$G$63:$G$67<L12))+1),Scorecard!$D$69) -> 0.32248451 | AG12: =Inputs!$B$10+Scorecard!$J$5*Y12+Scorecard!$J$6*Z12+Scorecard!$J$7*AA12+Scorecard!$J$8*AB12+Scorecard!$J$9*AC12+Scorecard!$J$10*AD12+Scorecard!$J$11*AE12+Scorecard!$J$12*AF12 -> -6.7372628 | AH12: =MIN(1-Inputs!$B$13,MAX(Inputs!$B$13,1/(1+EXP(-(Inputs!$B$11*AG12+Inputs!$B$12))))) -> 0.00093023591 | AI12: =Inputs!$B$9-Inputs!$B$8*AG12 -> 681.51919 | AJ12: =RANK(AH12,$AH$5:$AH$2004,0)+COUNTIF($AH$4:AH11,AH12) -> 1923 | AK12: =IF(AJ12<=Deciles!$B$5*(Deciles!$B$4+1),INT((AJ12-1)/(Deciles!$B$4+1))+1,Deciles!$B$5+INT((AJ12-1-Deciles!$B$5*(Deciles!$B$4+1))/Deciles!$B$4)+1) -> 10
A13: 365 | B13: 2022-07-31 | C13: 697 | D13: 82.980789 | E13: 72.61911 | F13: 17 | G13: 3.7019999 | H13: -2.0313332 | I13: 23 | J13: 10.876852 | K13: 5.0083332 | L13: -1.125 | M13: 6.2885799 | N13: 0 | O13: 0 | P13: C | Q13: O | R13: 2 | S13: CA | T13: 0 | U13: 52936.7 | V13: 0.01849054 | W13: 600.12878 | X13: 0.011495742 | Y13: =IF(ISNUMBER(C13),INDEX(Scorecard!$D$5:$D$12,SUMPRODUCT(--(Scorecard!$G$5:$G$11<C13))+1),Scorecard!$D$13) -> -0.86967785 | Z13: =IF(ISNUMBER(D13),INDEX(Scorecard!$D$14:$D$17,SUMPRODUCT(--(Scorecard!$G$14:$G$16<D13))+1),Scorecard!$D$18) -> 0.050535548 | AA13: =IF(ISNUMBER(E13),INDEX(Scorecard!$D$19:$D$26,SUMPRODUCT(--(Scorecard!$G$19:$G$25<E13))+1),Scorecard!$D$27) -> -0.034157851 | AB13: =IF(ISNUMBER(F13),INDEX(Scorecard!$D$28:$D$35,SUMPRODUCT(--(Scorecard!$G$28:$G$34<F13))+1),Scorecard!$D$36) -> 0.62482919 | AC13: =IF(ISNUMBER(H13),INDEX(Scorecard!$D$37:$D$44,SUMPRODUCT(--(Scorecard!$G$37:$G$43<H13))+1),Scorecard!$D$45) -> 1.3505764 | AD13: =IF(ISNUMBER(I13),INDEX(Scorecard!$D$46:$D$52,SUMPRODUCT(--(Scorecard!$G$46:$G$51<I13))+1),Scorecard!$D$53) -> -0.048559051 | AE13: =IF(ISNUMBER(K13),INDEX(Scorecard!$D$54:$D$61,SUMPRODUCT(--(Scorecard!$G$54:$G$60<K13))+1),Scorecard!$D$62) -> 0.21442935 | AF13: =IF(ISNUMBER(L13),INDEX(Scorecard!$D$63:$D$68,SUMPRODUCT(--(Scorecard!$G$63:$G$67<L13))+1),Scorecard!$D$69) -> -0.34058219 | AG13: =Inputs!$B$10+Scorecard!$J$5*Y13+Scorecard!$J$6*Z13+Scorecard!$J$7*AA13+Scorecard!$J$8*AB13+Scorecard!$J$9*AC13+Scorecard!$J$10*AD13+Scorecard!$J$11*AE13+Scorecard!$J$12*AF13 -> -3.9164867 | AH13: =MIN(1-Inputs!$B$13,MAX(Inputs!$B$13,1/(1+EXP(-(Inputs!$B$11*AG13+Inputs!$B$12))))) -> 0.018490539 | AI13: =Inputs!$B$9-Inputs!$B$8*AG13 -> 600.12879 | AJ13: =RANK(AH13,$AH$5:$AH$2004,0)+COUNTIF($AH$4:AH12,AH13) -> 489 | AK13: =IF(AJ13<=Deciles!$B$5*(Deciles!$B$4+1),INT((AJ13-1)/(Deciles!$B$4+1))+1,Deciles!$B$5+INT((AJ13-1-Deciles!$B$5*(Deciles!$B$4+1))/Deciles!$B$4)+1) -> 3
A14: 384 | B14: 2020-07-31 | C14: 714 | D14: 95.255974 | E14: 94.569649 | F14: 44 | G14: 4.0370002 | H14: 0.80366683 | I14: 5 | J14: 11.761801 | K14: 9.0333338 | L14: 5.0717955 | M14: 2.4695024 | N14: 0 | O14: 0 | P14: P | Q14: O | R14: 2 | S14: FL | T14: 1 | U14: 128258.19 | V14: 0.078584529 | W14: 559.25928 | X14: 0.25183254 | Y14: =IF(ISNUMBER(C14),INDEX(Scorecard!$D$5:$D$12,SUMPRODUCT(--(Scorecard!$G$5:$G$11<C14))+1),Scorecard!$D$13) -> -0.029042411 | Z14: =IF(ISNUMBER(D14),INDEX(Scorecard!$D$14:$D$17,SUMPRODUCT(--(Scorecard!$G$14:$G$16<D14))+1),Scorecard!$D$18) -> -0.36197087 | AA14: =IF(ISNUMBER(E14),INDEX(Scorecard!$D$19:$D$26,SUMPRODUCT(--(Scorecard!$G$19:$G$25<E14))+1),Scorecard!$D$27) -> -0.82099237 | AB14: =IF(ISNUMBER(F14),INDEX(Scorecard!$D$28:$D$35,SUMPRODUCT(--(Scorecard!$G$28:$G$34<F14))+1),Scorecard!$D$36) -> -0.30972704 | AC14: =IF(ISNUMBER(H14),INDEX(Scorecard!$D$37:$D$44,SUMPRODUCT(--(Scorecard!$G$37:$G$43<H14))+1),Scorecard!$D$45) -> -0.56945472 | AD14: =IF(ISNUMBER(I14),INDEX(Scorecard!$D$46:$D$52,SUMPRODUCT(--(Scorecard!$G$46:$G$51<I14))+1),Scorecard!$D$53) -> -0.16153484 | AE14: =IF(ISNUMBER(K14),INDEX(Scorecard!$D$54:$D$61,SUMPRODUCT(--(Scorecard!$G$54:$G$60<K14))+1),Scorecard!$D$62) -> -0.54191718 | AF14: =IF(ISNUMBER(L14),INDEX(Scorecard!$D$63:$D$68,SUMPRODUCT(--(Scorecard!$G$63:$G$67<L14))+1),Scorecard!$D$69) -> 0.32248451 | AG14: =Inputs!$B$10+Scorecard!$J$5*Y14+Scorecard!$J$6*Z14+Scorecard!$J$7*AA14+Scorecard!$J$8*AB14+Scorecard!$J$9*AC14+Scorecard!$J$10*AD14+Scorecard!$J$11*AE14+Scorecard!$J$12*AF14 -> -2.5000565 | AH14: =MIN(1-Inputs!$B$13,MAX(Inputs!$B$13,1/(1+EXP(-(Inputs!$B$11*AG14+Inputs!$B$12))))) -> 0.078584532 | AI14: =Inputs!$B$9-Inputs!$B$8*AG14 -> 559.25926 | AJ14: =RANK(AH14,$AH$5:$AH$2004,0)+COUNTIF($AH$4:AH13,AH14) -> 67 | AK14: =IF(AJ14<=Deciles!$B$5*(Deciles!$B$4+1),INT((AJ14-1)/(Deciles!$B$4+1))+1,Deciles!$B$5+INT((AJ14-1-Deciles!$B$5*(Deciles!$B$4+1))/Deciles!$B$4)+1) -> 1
A15: 443 | B15: 2023-01-31 | C15: 785 | D15: 80 | E15: 62.999836 | F15: 40 | G15: 4.474 | H15: -1.9593334 | I15: 53 | J15: 12.122337 | K15: 3.7 | L15: -0.45833325 | M15: 4.7441583 | N15: 0 | O15: 0 | P15: P | Q15: O | R15: 2 | S15: TX | T15: 0 | U15: 183935 | V15: 0.0026855436 | W15: 652.77814 | X15: 0.0012618864 | Y15: =IF(ISNUMBER(C15),INDEX(Scorecard!$D$5:$D$12,SUMPRODUCT(--(Scorecard!$G$5:$G$11<C15))+1),Scorecard!$D$13) -> 1.2375038 | Z15: =IF(ISNUMBER(D15),INDEX(Scorecard!$D$14:$D$17,SUMPRODUCT(--(Scorecard!$G$14:$G$16<D15))+1),Scorecard!$D$18) -> 0.050535548 | AA15: =IF(ISNUMBER(E15),INDEX(Scorecard!$D$19:$D$26,SUMPRODUCT(--(Scorecard!$G$19:$G$25<E15))+1),Scorecard!$D$27) -> 0.23362161 | AB15: =IF(ISNUMBER(F15),INDEX(Scorecard!$D$28:$D$35,SUMPRODUCT(--(Scorecard!$G$28:$G$34<F15))+1),Scorecard!$D$36) -> -0.13261687 | AC15: =IF(ISNUMBER(H15),INDEX(Scorecard!$D$37:$D$44,SUMPRODUCT(--(Scorecard!$G$37:$G$43<H15))+1),Scorecard!$D$45) -> 1.3505764 | AD15: =IF(ISNUMBER(I15),INDEX(Scorecard!$D$46:$D$52,SUMPRODUCT(--(Scorecard!$G$46:$G$51<I15))+1),Scorecard!$D$53) -> 0.81888237 | AE15: =IF(ISNUMBER(K15),INDEX(Scorecard!$D$54:$D$61,SUMPRODUCT(--(Scorecard!$G$54:$G$60<K15))+1),Scorecard!$D$62) -> 0.4890505 | AF15: =IF(ISNUMBER(L15),INDEX(Scorecard!$D$63:$D$68,SUMPRODUCT(--(Scorecard!$G$63:$G$67<L15))+1),Scorecard!$D$69) -> 0.32248451 | AG15: =Inputs!$B$10+Scorecard!$J$5*Y15+Scorecard!$J$6*Z15+Scorecard!$J$7*AA15+Scorecard!$J$8*AB15+Scorecard!$J$9*AC15+Scorecard!$J$10*AD15+Scorecard!$J$11*AE15+Scorecard!$J$12*AF15 -> -5.7411737 | AH15: =MIN(1-Inputs!$B$13,MAX(Inputs!$B$13,1/(1+EXP(-(Inputs!$B$11*AG15+Inputs!$B$12))))) -> 0.0026855437 | AI15: =Inputs!$B$9-Inputs!$B$8*AG15 -> 652.77813 | AJ15: =RANK(AH15,$AH$5:$AH$2004,0)+COUNTIF($AH$4:AH14,AH15) -> 1601 | AK15: =IF(AJ15<=Deciles!$B$5*(Deciles!$B$4+1),INT((AJ15-1)/(Deciles!$B$4+1))+1,Deciles!$B$5+INT((AJ15-1-Deciles!$B$5*(Deciles!$B$4+1))/Deciles!$B$4)+1) -> 9
A16: 444 | B16: 2020-01-31 | C16: 731 | D16: 80 | E16: 56.524651 | F16: 14 | G16: 4.2859998 | H16: 0.40266633 | I16: 53 | J16: 11.980857 | K16: 4.4230771 | L16: -0.2769227 | M16: 5.7497625 | N16: 0 | O16: 0 | P16: P | Q16: O | R16: 2 | S16: CA | T16: 0 | U16: 159668.86 | V16: 0.0045707906 | W16: 638.33411 | X16: 0.0022821566 | Y16: =IF(ISNUMBER(C16),INDEX(Scorecard!$D$5:$D$12,SUMPRODUCT(--(Scorecard!$G$5:$G$11<C16))+1),Scorecard!$D$13) -> -0.029042411 | Z16: =IF(ISNUMBER(D16),INDEX(Scorecard!$D$14:$D$17,SUMPRODUCT(--(Scorecard!$G$14:$G$16<D16))+1),Scorecard!$D$18) -> 0.050535548 | AA16: =IF(ISNUMBER(E16),INDEX(Scorecard!$D$19:$D$26,SUMPRODUCT(--(Scorecard!$G$19:$G$25<E16))+1),Scorecard!$D$27) -> 0.28589934 | AB16: =IF(ISNUMBER(F16),INDEX(Scorecard!$D$28:$D$35,SUMPRODUCT(--(Scorecard!$G$28:$G$34<F16))+1),Scorecard!$D$36) -> 0.62482919 | AC16: =IF(ISNUMBER(H16),INDEX(Scorecard!$D$37:$D$44,SUMPRODUCT(--(Scorecard!$G$37:$G$43<H16))+1),Scorecard!$D$45) -> -0.27122968 | AD16: =IF(ISNUMBER(I16),INDEX(Scorecard!$D$46:$D$52,SUMPRODUCT(--(Scorecard!$G$46:$G$51<I16))+1),Scorecard!$D$53) -> 0.81888237 | AE16: =IF(ISNUMBER(K16),INDEX(Scorecard!$D$54:$D$61,SUMPRODUCT(--(Scorecard!$G$54:$G$60<K16))+1),Scorecard!$D$62) -> 0.409483 | AF16: =IF(ISNUMBER(L16),INDEX(Scorecard!$D$63:$D$68,SUMPRODUCT(--(Scorecard!$G$63:$G$67<L16))+1),Scorecard!$D$69) -> 0.32248451 | AG16: =Inputs!$B$10+Scorecard!$J$5*Y16+Scorecard!$J$6*Z16+Scorecard!$J$7*AA16+Scorecard!$J$8*AB16+Scorecard!$J$9*AC16+Scorecard!$J$10*AD16+Scorecard!$J$11*AE16+Scorecard!$J$12*AF16 -> -5.2405819 | AH16: =MIN(1-Inputs!$B$13,MAX(Inputs!$B$13,1/(1+EXP(-(Inputs!$B$11*AG16+Inputs!$B$12))))) -> 0.0045707905 | AI16: =Inputs!$B$9-Inputs!$B$8*AG16 -> 638.33411 | AJ16: =RANK(AH16,$AH$5:$AH$2004,0)+COUNTIF($AH$4:AH15,AH16) -> 1311 | AK16: =IF(AJ16<=Deciles!$B$5*(Deciles!$B$4+1),INT((AJ16-1)/(Deciles!$B$4+1))+1,Deciles!$B$5+INT((AJ16-1-Deciles!$B$5*(Deciles!$B$4+1))/Deciles!$B$4)+1) -> 7
... A2004: 59999 | B2004: 2021-07-31 | C2004: 763 | D2004: 80 | E2004: 66.766762 | F2004: 43 | G2004: 4.1900001 | H2004: 1.1733334 | I2004: 42 | J2004: 12.40171 | K2004: 5.4333334 | L2004: -3.5 | M2004: 2.7406642 | N2004: 0 | O2004: 0 | P2004: P | Q2004: I | R2004: 1 | S2004: GA | T2004: 0 | U2004: 243217.12 | V2004: 0.0058801547 | W2004: 631.48108 | X2004: 0.0059091309 | Y2004: =IF(ISNUMBER(C2004),INDEX(Scorecard!$D$5:$D$12,SUMPRODUCT(--(Scorecard!$G$5:$G$11<C2004))+1),Scorecard!$D$13) -> 1.2375038 | Z2004: =IF(ISNUMBER(D2004),INDEX(Scorecard!$D$14:$D$17,SUMPRODUCT(--(Scorecard!$G$14:$G$16<D2004))+1),Scorecard!$D$18) -> 0.050535548 | AA2004: =IF(ISNUMBER(E2004),INDEX(Scorecard!$D$19:$D$26,SUMPRODUCT(--(Scorecard!$G$19:$G$25<E2004))+1),Scorecard!$D$27) -> 0.053084309 | AB2004: =IF(ISNUMBER(F2004),INDEX(Scorecard!$D$28:$D$35,SUMPRODUCT(--(Scorecard!$G$28:$G$34<F2004))+1),Scorecard!$D$36) -> -0.30972704 | AC2004: =IF(ISNUMBER(H2004),INDEX(Scorecard!$D$37:$D$44,SUMPRODUCT(--(Scorecard!$G$37:$G$43<H2004))+1),Scorecard!$D$45) -> -0.97550357 | AD2004: =IF(ISNUMBER(I2004),INDEX(Scorecard!$D$46:$D$52,SUMPRODUCT(--(Scorecard!$G$46:$G$51<I2004))+1),Scorecard!$D$53) -> 0.56987541 | AE2004: =IF(ISNUMBER(K2004),INDEX(Scorecard!$D$54:$D$61,SUMPRODUCT(--(Scorecard!$G$54:$G$60<K2004))+1),Scorecard!$D$62) -> 0.12630355 | AF2004: =IF(ISNUMBER(L2004),INDEX(Scorecard!$D$63:$D$68,SUMPRODUCT(--(Scorecard!$G$63:$G$67<L2004))+1),Scorecard!$D$69) -> -0.34058219 | AG2004: =Inputs!$B$10+Scorecard!$J$5*Y2004+Scorecard!$J$6*Z2004+Scorecard!$J$7*AA2004+Scorecard!$J$8*AB2004+Scorecard!$J$9*AC2004+Scorecard!$J$10*AD2004+Scorecard!$J$11*AE2004+Scorecard!$J$12*AF2004 -> -5.0030747 | AH2004: =MIN(1-Inputs!$B$13,MAX(Inputs!$B$13,1/(1+EXP(-(Inputs!$B$11*AG2004+Inputs!$B$12))))) -> 0.0058801546 | AI2004: =Inputs!$B$9-Inputs!$B$8*AG2004 -> 631.4811 | AJ2004: =RANK(AH2004,$AH$5:$AH$2004,0)+COUNTIF($AH$4:AH2003,AH2004) -> 1154 | AK2004: =IF(AJ2004<=Deciles!$B$5*(Deciles!$B$4+1),INT((AJ2004-1)/(Deciles!$B$4+1))+1,Deciles!$B$5+INT((AJ2004-1-Deciles!$B$5*(Deciles!$B$4+1))/Deciles!$B$4)+1) -> 6

Sheet Deciles
A1: Decile table over the live scorecard PD (descending score, ties broken by input order, as in evaluation.decile_table)
A3: Loans | B3: =COUNT(Loan_Sample!$AH$5:$AH$2004) -> 2000
A4: Base group size | B4: =INT(B3/10) -> 200
A5: Groups with one extra loan | B5: =MOD(B3,10) -> 0
A9: decile | B9: n | C9: events | D9: event_rate | E9: mean_pd | F9: cum_events_share | G9: lift | H9: ks_at_decile | I9: cum_nonevents_share | J9: roc_trapezoid_area | L9: py_full_oot_event_rate | M9: py_full_oot_mean_score | N9: py_full_oot_ks
A10: =ROW()-9 -> 1 | B10: =COUNTIFS(Loan_Sample!$AK$5:$AK$2004,A10) -> 200 | C10: =SUMIFS(Loan_Sample!$T$5:$T$2004,Loan_Sample!$AK$5:$AK$2004,A10) -> 15 | D10: =C10/B10 -> 0.075 | E10: =SUMIFS(Loan_Sample!$AH$5:$AH$2004,Loan_Sample!$AK$5:$AK$2004,A10)/B10 -> 0.079133909 | F10: =SUM(C$10:C10)/SUM(C$10:C$19) -> 0.38461538 | G10: =D10/(SUM(C$10:C$19)/SUM(B$10:B$19)) -> 3.8461538 | H10: =ABS(F10-I10) -> 0.29027576 | I10: =(SUM(B$10:B10)-SUM(C$10:C10))/(SUM(B$10:B$19)-SUM(C$10:C$19)) -> 0.094339623 | J10: =(I10-0)*(F10+0)/2 -> 0.018142235 | L10: =Python_Ref!D5 -> 0.10186386 | M10: =Python_Ref!E5 -> 0.08576315 | N10: =Python_Ref!H5 -> 0.34709926
A11: =ROW()-9 -> 2 | B11: =COUNTIFS(Loan_Sample!$AK$5:$AK$2004,A11) -> 200 | C11: =SUMIFS(Loan_Sample!$T$5:$T$2004,Loan_Sample!$AK$5:$AK$2004,A11) -> 8 | D11: =C11/B11 -> 0.04 | E11: =SUMIFS(Loan_Sample!$AH$5:$AH$2004,Loan_Sample!$AK$5:$AK$2004,A11)/B11 -> 0.031468024 | F11: =SUM(C$10:C11)/SUM(C$10:C$19) -> 0.58974359 | G11: =D11/(SUM(C$10:C$19)/SUM(B$10:B$19)) -> 2.0512821 | H11: =ABS(F11-I11) -> 0.39749474 | I11: =(SUM(B$10:B11)-SUM(C$10:C11))/(SUM(B$10:B$19)-SUM(C$10:C$19)) -> 0.19224885 | J11: =(I11-I10)*(F11+F10)/2 -> 0.047699368 | L11: =Python_Ref!D6 -> 0.039789303 | M11: =Python_Ref!E6 -> 0.03075779 | N11: =Python_Ref!H6 -> 0.42029185
A12: =ROW()-9 -> 3 | B12: =COUNTIFS(Loan_Sample!$AK$5:$AK$2004,A12) -> 200 | C12: =SUMIFS(Loan_Sample!$T$5:$T$2004,Loan_Sample!$AK$5:$AK$2004,A12) -> 2 | D12: =C12/B12 -> 0.01 | E12: =SUMIFS(Loan_Sample!$AH$5:$AH$2004,Loan_Sample!$AK$5:$AK$2004,A12)/B12 -> 0.018481236 | F12: =SUM(C$10:C12)/SUM(C$10:C$19) -> 0.64102564 | G12: =D12/(SUM(C$10:C$19)/SUM(B$10:B$19)) -> 0.51282051 | H12: =ABS(F12-I12) -> 0.34780789 | I12: =(SUM(B$10:B12)-SUM(C$10:C12))/(SUM(B$10:B$19)-SUM(C$10:C$19)) -> 0.29321775 | J12: =(I12-I11)*(F12+F11)/2 -> 0.062134704 | L12: =Python_Ref!D7 -> 0.02439222 | M12: =Python_Ref!E7 -> 0.01860216 | N12: =Python_Ref!H7 -> 0.42554413
A13: =ROW()-9 -> 4 | B13: =COUNTIFS(Loan_Sample!$AK$5:$AK$2004,A13) -> 200 | C13: =SUMIFS(Loan_Sample!$T$5:$T$2004,Loan_Sample!$AK$5:$AK$2004,A13) -> 2 | D13: =C13/B13 -> 0.01 | E13: =SUMIFS(Loan_Sample!$AH$5:$AH$2004,Loan_Sample!$AK$5:$AK$2004,A13)/B13 -> 0.012332417 | F13: =SUM(C$10:C13)/SUM(C$10:C$19) -> 0.69230769 | G13: =D13/(SUM(C$10:C$19)/SUM(B$10:B$19)) -> 0.51282051 | H13: =ABS(F13-I13) -> 0.29812105 | I13: =(SUM(B$10:B13)-SUM(C$10:C13))/(SUM(B$10:B$19)-SUM(C$10:C$19)) -> 0.39418664 | J13: =(I13-I12)*(F13+F12)/2 -> 0.067312596 | L13: =Python_Ref!D8 -> 0.019692058 | M13: =Python_Ref!E8 -> 0.012607254 | N13: =Python_Ref!H8 -> 0.41005675
A14: =ROW()-9 -> 5 | B14: =COUNTIFS(Loan_Sample!$AK$5:$AK$2004,A14) -> 200 | C14: =SUMIFS(Loan_Sample!$T$5:$T$2004,Loan_Sample!$AK$5:$AK$2004,A14) -> 2 | D14: =C14/B14 -> 0.01 | E14: =SUMIFS(Loan_Sample!$AH$5:$AH$2004,Loan_Sample!$AK$5:$AK$2004,A14)/B14 -> 0.0088894804 | F14: =SUM(C$10:C14)/SUM(C$10:C$19) -> 0.74358974 | G14: =D14/(SUM(C$10:C$19)/SUM(B$10:B$19)) -> 0.51282051 | H14: =ABS(F14-I14) -> 0.24843421 | I14: =(SUM(B$10:B14)-SUM(C$10:C14))/(SUM(B$10:B$19)-SUM(C$10:C$19)) -> 0.49515553 | J14: =(I14-I13)*(F14+F13)/2 -> 0.072490488 | L14: =Python_Ref!D9 -> 0.01547812 | M14: =Python_Ref!E9 -> 0.0089404946 | N14: =Python_Ref!H9 -> 0.37597518
A15: =ROW()-9 -> 6 | B15: =COUNTIFS(Loan_Sample!$AK$5:$AK$2004,A15) -> 200 | C15: =SUMIFS(Loan_Sample!$T$5:$T$2004,Loan_Sample!$AK$5:$AK$2004,A15) -> 5 | D15: =C15/B15 -> 0.025 | E15: =SUMIFS(Loan_Sample!$AH$5:$AH$2004,Loan_Sample!$AK$5:$AK$2004,A15)/B15 -> 0.0064882478 | F15: =SUM(C$10:C15)/SUM(C$10:C$19) -> 0.87179487 | G15: =D15/(SUM(C$10:C$19)/SUM(B$10:B$19)) -> 1.2820513 | H15: =ABS(F15-I15) -> 0.27720028 | I15: =(SUM(B$10:B15)-SUM(C$10:C15))/(SUM(B$10:B$19)-SUM(C$10:C$19)) -> 0.59459459 | J15: =(I15-I14)*(F15+F14)/2 -> 0.080316165 | L15: =Python_Ref!D10 -> 0.012075533 | M15: =Python_Ref!E10 -> 0.0064334323 | N15: =Python_Ref!H10 -> 0.32688352
A16: =ROW()-9 -> 7 | B16: =COUNTIFS(Loan_Sample!$AK$5:$AK$2004,A16) -> 200 | C16: =SUMIFS(Loan_Sample!$T$5:$T$2004,Loan_Sample!$AK$5:$AK$2004,A16) -> 4 | D16: =C16/B16 -> 0.02 | E16: =SUMIFS(Loan_Sample!$AH$5:$AH$2004,Loan_Sample!$AK$5:$AK$2004,A16)/B16 -> 0.0046411069 | F16: =SUM(C$10:C16)/SUM(C$10:C$19) -> 0.97435897 | G16: =D16/(SUM(C$10:C$19)/SUM(B$10:B$19)) -> 1.025641 | H16: =ABS(F16-I16) -> 0.27981537 | I16: =(SUM(B$10:B16)-SUM(C$10:C16))/(SUM(B$10:B$19)-SUM(C$10:C$19)) -> 0.6945436 | J16: =(I16-I15)*(F16+F15)/2 -> 0.092260621 | L16: =Python_Ref!D11 -> 0.0074560337 | M16: =Python_Ref!E11 -> 0.004548491 | N16: =Python_Ref!H11 -> 0.25740977
A17: =ROW()-9 -> 8 | B17: =COUNTIFS(Loan_Sample!$AK$5:$AK$2004,A17) -> 200 | C17: =SUMIFS(Loan_Sample!$T$5:$T$2004,Loan_Sample!$AK$5:$AK$2004,A17) -> 0 | D17: =C17/B17 -> 0 | E17: =SUMIFS(Loan_Sample!$AH$5:$AH$2004,Loan_Sample!$AK$5:$AK$2004,A17)/B17 -> 0.003244281 | F17: =SUM(C$10:C17)/SUM(C$10:C$19) -> 0.97435897 | G17: =D17/(SUM(C$10:C$19)/SUM(B$10:B$19)) -> 0 | H17: =ABS(F17-I17) -> 0.17782659 | I17: =(SUM(B$10:B17)-SUM(C$10:C17))/(SUM(B$10:B$19)-SUM(C$10:C$19)) -> 0.79653238 | J17: =(I17-I16)*(F17+F16)/2 -> 0.099373684 | L17: =Python_Ref!D12 -> 0.0052678499 | M17: =Python_Ref!E12 -> 0.0030592419 | N17: =Python_Ref!H12 -> 0.17828135
A18: =ROW()-9 -> 9 | B18: =COUNTIFS(Loan_Sample!$AK$5:$AK$2004,A18) -> 200 | C18: =SUMIFS(Loan_Sample!$T$5:$T$2004,Loan_Sample!$AK$5:$AK$2004,A18) -> 0 | D18: =C18/B18 -> 0 | E18: =SUMIFS(Loan_Sample!$AH$5:$AH$2004,Loan_Sample!$AK$5:$AK$2004,A18)/B18 -> 0.0020251289 | F18: =SUM(C$10:C18)/SUM(C$10:C$19) -> 0.97435897 | G18: =D18/(SUM(C$10:C$19)/SUM(B$10:B$19)) -> 0 | H18: =ABS(F18-I18) -> 0.075837812 | I18: =(SUM(B$10:B18)-SUM(C$10:C18))/(SUM(B$10:B$19)-SUM(C$10:C$19)) -> 0.89852116 | J18: =(I18-I17)*(F18+F17)/2 -> 0.099373684 | L18: =Python_Ref!D13 -> 0.0035659292 | M18: =Python_Ref!E13 -> 0.0018769678 | N18: =Python_Ref!H13 -> 0.091643739
A19: =ROW()-9 -> 10 | B19: =COUNTIFS(Loan_Sample!$AK$5:$AK$2004,A19) -> 200 | C19: =SUMIFS(Loan_Sample!$T$5:$T$2004,Loan_Sample!$AK$5:$AK$2004,A19) -> 1 | D19: =C19/B19 -> 0.005 | E19: =SUMIFS(Loan_Sample!$AH$5:$AH$2004,Loan_Sample!$AK$5:$AK$2004,A19)/B19 -> 0.0010130492 | F19: =SUM(C$10:C19)/SUM(C$10:C$19) -> 1 | G19: =D19/(SUM(C$10:C$19)/SUM(B$10:B$19)) -> 0.25641026 | H19: =ABS(F19-I19) -> 0 | I19: =(SUM(B$10:B19)-SUM(C$10:C19))/(SUM(B$10:B$19)-SUM(C$10:C$19)) -> 1 | J19: =(I19-I18)*(F19+F18)/2 -> 0.10017783 | L19: =Python_Ref!D14 -> 0.0024313153 | M19: =Python_Ref!E14 -> 0.00095519046 | N19: =Python_Ref!H14 -> 0
A21: Max KS (decile based) | B21: =MAX(H10:H19) -> 0.39749474
A22: AUC, approximate (decile ROC trapezoid) | B22: =SUM(J10:J19) -> 0.73928137
A23: Gini, approximate (2 x AUC - 1) | B23: =2*B22-1 -> 0.47856274

Sheet PSI
A1: Population stability index of the scorecard PD: training quantile bins vs the 2,000-loan sample (live)
A3: Share floor | B3: =Inputs!$B$19 -> 0.0001
A4: Band thresholds (stable below / moderate below) | B4: =Inputs!$B$20 -> 0.1 | C4: =Inputs!$B$21 -> 0.25
A6: bin | B6: lo (exclusive) | C6: hi (inclusive) | D6: expected_share | E6: actual_share | F6: actual_count | G6: expected_floored | H6: actual_floored | I6: psi_contribution
A7: =Python_Ref!A19 -> 1 | B7: =Python_Ref!B19 -> -1 | C7: =Python_Ref!C19 -> 0.0016046033 | D7: =Python_Ref!D19 -> 0.10000141 | E7: =F7/SUM(F$7:F$16) -> 0.1085 | F7: =SUMPRODUCT((Loan_Sample!$AH$5:$AH$2004>B7)*(Loan_Sample!$AH$5:$AH$2004<=C7)) -> 217 | G7: =MAX(D7,$B$3) -> 0.10000141 | H7: =MAX(E7,$B$3) -> 0.1085 | I7: =(H7-G7)*LN(H7/G7) -> 0.00069319506
A8: =Python_Ref!A20 -> 2 | B8: =Python_Ref!B20 -> 0.0016046033 | C8: =Python_Ref!C20 -> 0.0027144069 | D8: =Python_Ref!D20 -> 0.10000141 | E8: =F8/SUM(F$7:F$16) -> 0.0955 | F8: =SUMPRODUCT((Loan_Sample!$AH$5:$AH$2004>B8)*(Loan_Sample!$AH$5:$AH$2004<=C8)) -> 191 | G8: =MAX(D8,$B$3) -> 0.10000141 | H8: =MAX(E8,$B$3) -> 0.0955 | I8: =(H8-G8)*LN(H8/G8) -> 0.0002073261
A9: =Python_Ref!A21 -> 3 | B9: =Python_Ref!B21 -> 0.0027144069 | C9: =Python_Ref!C21 -> 0.0042681407 | D9: =Python_Ref!D21 -> 0.10000846 | E9: =F9/SUM(F$7:F$16) -> 0.1215 | F9: =SUMPRODUCT((Loan_Sample!$AH$5:$AH$2004>B9)*(Loan_Sample!$AH$5:$AH$2004<=C9)) -> 243 | G9: =MAX(D9,$B$3) -> 0.10000846 | H9: =MAX(E9,$B$3) -> 0.1215 | I9: =(H9-G9)*LN(H9/G9) -> 0.0041835324
A10: =Python_Ref!A22 -> 4 | B10: =Python_Ref!B22 -> 0.0042681407 | C10: =Python_Ref!C22 -> 0.006159664 | D10: =Python_Ref!D22 -> 0.099987311 | E10: =F10/SUM(F$7:F$16) -> 0.109 | F10: =SUMPRODUCT((Loan_Sample!$AH$5:$AH$2004>B10)*(Loan_Sample!$AH$5:$AH$2004<=C10)) -> 218 | G10: =MAX(D10,$B$3) -> 0.099987311 | H10: =MAX(E10,$B$3) -> 0.109 | I10: =(H10-G10)*LN(H10/G10) -> 0.00077783642
A11: =Python_Ref!A23 -> 5 | B11: =Python_Ref!B23 -> 0.006159664 | C11: =Python_Ref!C23 -> 0.0085888519 | D11: =Python_Ref!D23 -> 0.10000141 | E11: =F11/SUM(F$7:F$16) -> 0.108 | F11: =SUMPRODUCT((Loan_Sample!$AH$5:$AH$2004>B11)*(Loan_Sample!$AH$5:$AH$2004<=C11)) -> 216 | G11: =MAX(D11,$B$3) -> 0.10000141 | H11: =MAX(E11,$B$3) -> 0.108 | I11: =(H11-G11)*LN(H11/G11) -> 0.00061546706
A12: =Python_Ref!A24 -> 6 | B12: =Python_Ref!B24 -> 0.0085888519 | C12: =Python_Ref!C24 -> 0.01205079 | D12: =Python_Ref!D24 -> 0.10000141 | E12: =F12/SUM(F$7:F$16) -> 0.104 | F12: =SUMPRODUCT((Loan_Sample!$AH$5:$AH$2004>B12)*(Loan_Sample!$AH$5:$AH$2004<=C12)) -> 208 | G12: =MAX(D12,$B$3) -> 0.10000141 | H12: =MAX(E12,$B$3) -> 0.104 | I12: =(H12-G12)*LN(H12/G12) -> 0.00015677118
A13: =Python_Ref!A25 -> 7 | B13: =Python_Ref!B25 -> 0.01205079 | C13: =Python_Ref!C25 -> 0.017188131 | D13: =Python_Ref!D25 -> 0.10000846 | E13: =F13/SUM(F$7:F$16) -> 0.094 | F13: =SUMPRODUCT((Loan_Sample!$AH$5:$AH$2004>B13)*(Loan_Sample!$AH$5:$AH$2004<=C13)) -> 188 | G13: =MAX(D13,$B$3) -> 0.10000846 | H13: =MAX(E13,$B$3) -> 0.094 | I13: =(H13-G13)*LN(H13/G13) -> 0.00037228408
A14: =Python_Ref!A26 -> 8 | B14: =Python_Ref!B26 -> 0.017188131 | C14: =Python_Ref!C26 -> 0.026642986 | D14: =Python_Ref!D26 -> 0.099987311 | E14: =F14/SUM(F$7:F$16) -> 0.083 | F14: =SUMPRODUCT((Loan_Sample!$AH$5:$AH$2004>B14)*(Loan_Sample!$AH$5:$AH$2004<=C14)) -> 166 | G14: =MAX(D14,$B$3) -> 0.099987311 | H14: =MAX(E14,$B$3) -> 0.083 | I14: =(H14-G14)*LN(H14/G14) -> 0.0031630829
A15: =Python_Ref!A27 -> 9 | B15: =Python_Ref!B27 -> 0.026642986 | C15: =Python_Ref!C27 -> 0.047691937 | D15: =Python_Ref!D27 -> 0.10002256 | E15: =F15/SUM(F$7:F$16) -> 0.097 | F15: =SUMPRODUCT((Loan_Sample!$AH$5:$AH$2004>B15)*(Loan_Sample!$AH$5:$AH$2004<=C15)) -> 194 | G15: =MAX(D15,$B$3) -> 0.10002256 | H15: =MAX(E15,$B$3) -> 0.097 | I15: =(H15-G15)*LN(H15/G15) -> 9.2746459e-05
A16: =Python_Ref!A28 -> 10 | B16: =Python_Ref!B28 -> 0.047691937 | C16: =Python_Ref!C28 -> 2 | D16: =Python_Ref!D28 -> 0.099980262 | E16: =F16/SUM(F$7:F$16) -> 0.0795 | F16: =SUMPRODUCT((Loan_Sample!$AH$5:$AH$2004>B16)*(Loan_Sample!$AH$5:$AH$2004<=C16)) -> 159 | G16: =MAX(D16,$B$3) -> 0.099980262 | H16: =MAX(E16,$B$3) -> 0.0795 | I16: =(H16-G16)*LN(H16/G16) -> 0.0046943989
A18: Total PSI | B18: =SUM(I7:I16) -> 0.014956641
A19: Python PSI, train vs full OOT (pd_logit) | B19: =INDEX(Python_Ref!$C$33:$C$55,MATCH("pd_logit:train_vs_oot",Python_Ref!$B$33:$B$55,0)) -> 0.011827461
A20: Note: the training distribution is stored only for the score, so per-variable PSI is not recomputed live; Python CSI is on Python_Ref.

Sheet Calibration
A1: Calibration of the live scorecard PD by decile (decile 1 = highest predicted PD)
A3: decile | B3: n | C3: mean_predicted_pd | D3: observed_rate | E3: predicted_minus_observed | F3: expected_events | G3: events | H3: hosmer_lemeshow_term
A4: =Deciles!A10 -> 1 | B4: =Deciles!B10 -> 200 | C4: =Deciles!E10 -> 0.079133909 | D4: =Deciles!D10 -> 0.075 | E4: =C4-D4 -> 0.0041339087 | F4: =B4*C4 -> 15.826782 | G4: =Deciles!C10 -> 15 | H4: =(G4-F4)^2/(B4*C4*(1-C4)) -> 0.046902139
A5: =Deciles!A11 -> 2 | B5: =Deciles!B11 -> 200 | C5: =Deciles!E11 -> 0.031468024 | D5: =Deciles!D11 -> 0.04 | E5: =C5-D5 -> -0.0085319758 | F5: =B5*C5 -> 6.2936048 | G5: =Deciles!C11 -> 8 | H5: =(G5-F5)^2/(B5*C5*(1-C5)) -> 0.47768961
A6: =Deciles!A12 -> 3 | B6: =Deciles!B12 -> 200 | C6: =Deciles!E12 -> 0.018481236 | D6: =Deciles!D12 -> 0.01 | E6: =C6-D6 -> 0.0084812356 | F6: =B6*C6 -> 3.6962471 | G6: =Deciles!C12 -> 2 | H6: =(G6-F6)^2/(B6*C6*(1-C6)) -> 0.79308301
A7: =Deciles!A13 -> 4 | B7: =Deciles!B13 -> 200 | C7: =Deciles!E13 -> 0.012332417 | D7: =Deciles!D13 -> 0.01 | E7: =C7-D7 -> 0.0023324166 | F7: =B7*C7 -> 2.4664833 | G7: =Deciles!C13 -> 2 | H7: =(G7-F7)^2/(B7*C7*(1-C7)) -> 0.089327105
A8: =Deciles!A14 -> 5 | B8: =Deciles!B14 -> 200 | C8: =Deciles!E14 -> 0.0088894804 | D8: =Deciles!D14 -> 0.01 | E8: =C8-D8 -> -0.0011105196 | F8: =B8*C8 -> 1.7778961 | G8: =Deciles!C14 -> 2 | H8: =(G8-F8)^2/(B8*C8*(1-C8)) -> 0.027995228
A9: =Deciles!A15 -> 6 | B9: =Deciles!B15 -> 200 | C9: =Deciles!E15 -> 0.0064882478 | D9: =Deciles!D15 -> 0.025 | E9: =C9-D9 -> -0.018511752 | F9: =B9*C9 -> 1.2976496 | G9: =Deciles!C15 -> 5 | H9: =(G9-F9)^2/(B9*C9*(1-C9)) -> 10.632236
A10: =Deciles!A16 -> 7 | B10: =Deciles!B16 -> 200 | C10: =Deciles!E16 -> 0.0046411069 | D10: =Deciles!D16 -> 0.02 | E10: =C10-D10 -> -0.015358893 | F10: =B10*C10 -> 0.92822137 | G10: =Deciles!C16 -> 4 | H10: =(G10-F10)^2/(B10*C10*(1-C10)) -> 10.212888
A11: =Deciles!A17 -> 8 | B11: =Deciles!B17 -> 200 | C11: =Deciles!E17 -> 0.003244281 | D11: =Deciles!D17 -> 0 | E11: =C11-D11 -> 0.003244281 | F11: =B11*C11 -> 0.6488562 | G11: =Deciles!C17 -> 0 | H11: =(G11-F11)^2/(B11*C11*(1-C11)) -> 0.65096813
A12: =Deciles!A18 -> 9 | B12: =Deciles!B18 -> 200 | C12: =Deciles!E18 -> 0.0020251289 | D12: =Deciles!D18 -> 0 | E12: =C12-D12 -> 0.0020251289 | F12: =B12*C12 -> 0.40502579 | G12: =Deciles!C18 -> 0 | H12: =(G12-F12)^2/(B12*C12*(1-C12)) -> 0.40584768
A13: =Deciles!A19 -> 10 | B13: =Deciles!B19 -> 200 | C13: =Deciles!E19 -> 0.0010130492 | D13: =Deciles!D19 -> 0.005 | E13: =C13-D13 -> -0.0039869508 | F13: =B13*C13 -> 0.20260984 | G13: =Deciles!C19 -> 1 | H13: =(G13-F13)^2/(B13*C13*(1-C13)) -> 3.1413868
A15: Brier score (live) | B15: =SUMPRODUCT((Loan_Sample!$AH$5:$AH$2004-Loan_Sample!$T$5:$T$2004)^2)/COUNT(Loan_Sample!$AH$5:$AH$2004) -> 0.01860735
A16: Brier of a constant base-rate forecast | B16: =(SUM(G4:G13)/SUM(B4:B13))*(1-SUM(G4:G13)/SUM(B4:B13)) -> 0.01911975
A17: Hosmer-Lemeshow statistic (10 groups) | B17: =SUM(H4:H13) -> 26.478324
A18: Total expected events | B18: =SUM(F4:F13) -> 33.543376
A19: Total observed events | B19: =SUM(G4:G13) -> 39
A20: Expected / observed | B20: =B18/B19 -> 0.86008656

Sheet Scenario
A1: Scenario: selected shock applied to the 2,000-loan sample (scorecard re-binned on shocked attributes; prepay hinge logit)
A2: Shock mapping: unemp and unemp_chg_12m + unemp_pt; mtm_ltv / (1 + hpi_pct/100); incentive - rate_bp/100. Full shock applied at the snapshot (no ramp). The scorecard uses these four macro-sensitive variables directly, so no separate uplift table is needed.
A3: Selected scenario | B3: =Inputs!$B$23 -> Base
A5: Metric | B5: Base (no shock) | C5: Selected scenario | D5: Change
A6: Loans | B6: =COUNT(Loan_Sample!$AH$5:$AH$2004) -> 2000 | C6: =COUNT($L$25:$L$2024) -> 2000 | D6: =C6-B6 -> 0
A7: Total UPB (USD) | B7: =SUM($B$25:$B$2024) -> 4.5873175e+08 | C7: =SUM($B$25:$B$2024) -> 4.5873175e+08 | D7: =C7-B7 -> 0
A8: Expected 12-month defaults (sum of PD) | B8: =SUM(Loan_Sample!$AH$5:$AH$2004) -> 33.543376 | C8: =SUM($L$25:$L$2024) -> 33.543376 | D8: =C8-B8 -> 0
A9: UPB-weighted 12-month PD | B9: =SUMPRODUCT(Loan_Sample!$AH$5:$AH$2004,$B$25:$B$2024)/SUM($B$25:$B$2024) -> 0.016937138 | C9: =SUMPRODUCT($L$25:$L$2024,$B$25:$B$2024)/SUM($B$25:$B$2024) -> 0.016937138 | D9: =C9-B9 -> 0
A10: Expected loss = PD x LGD x UPB (USD) | B10: =SUM($M$25:$M$2024) -> 2719361 | C10: =SUM($N$25:$N$2024) -> 2719361 | D10: =C10-B10 -> 0
A11: Expected loss, % of UPB | B11: =SUM($M$25:$M$2024)/SUM($B$25:$B$2024) -> 0.0059279983 | C11: =SUM($N$25:$N$2024)/SUM($B$25:$B$2024) -> 0.0059279983 | D11: =C11-B11 -> 0
A12: UPB-weighted SMM (monthly prepay rate) | B12: =SUMPRODUCT($P$25:$P$2024,$B$25:$B$2024)/SUM($B$25:$B$2024) -> 0.010033587 | C12: =SUMPRODUCT($R$25:$R$2024,$B$25:$B$2024)/SUM($B$25:$B$2024) -> 0.010033587 | D12: =C12-B12 -> 0
A13: 12-month prepay at constant SMM = 1-(1-SMM)^12 (CPR) | B13: =1-(1-B12)^12 -> 0.11397592 | C13: =1-(1-C12)^12 -> 0.11397592 | D13: =C13-B13 -> 0
A14: 12-month default rate (CDR proxy) = UPB-weighted PD | B14: =B9 -> 0.016937138 | C14: =C9 -> 0.016937138 | D14: =C14-B14 -> 0
A16: Python GBM reference for the selected scenario (static curves, 12 months; context only)
A17: default_12m_pct_upb | C17: =INDEX(Python_Ref!$B$60:$B$65,MATCH($B$3,Python_Ref!$A$60:$A$65,0)) -> 1.0924484
A18: prepay_12m_pct_upb | C18: =INDEX(Python_Ref!$C$60:$C$65,MATCH($B$3,Python_Ref!$A$60:$A$65,0)) -> 11.378502
A19: avg_cpr_12m | C19: =INDEX(Python_Ref!$D$60:$D$65,MATCH($B$3,Python_Ref!$A$60:$A$65,0)) -> 0.11575516
A20: avg_cdr_12m | C20: =INDEX(Python_Ref!$E$60:$E$65,MATCH($B$3,Python_Ref!$A$60:$A$65,0)) -> 0.011631025
A21: Note: the GBM PD is insensitive to the rate shock; the scorecard moves only through its incentive variable.
A24: loan_id | B24: cur_upb | C24: unemp_s | D24: unemp_chg_s | E24: mtm_ltv_s | F24: incentive_s | G24: woe_s_unemp | H24: woe_s_unemp_chg_12m | I24: woe_s_mtm_ltv | J24: woe_s_incentive | K24: margin_s | L24: pd_s | M24: el_base | N24: el_s | O24: pp_margin_base | P24: smm_base | Q24: pp_margin_s | R24: smm_s
A25: =Loan_Sample!A5 -> 53 | B25: =Loan_Sample!U5 -> 234398.6 | C25: =Loan_Sample!K5+Inputs!$B$26 -> 5.4333334 | D25: =Loan_Sample!L5+Inputs!$B$26 -> -3.5 | E25: =Loan_Sample!E5/(1+Inputs!$B$25/100) -> 84.254295 | F25: =Loan_Sample!H5-Inputs!$B$24/100 -> 0.11933327 | G25: =IF(ISNUMBER(C25),INDEX(Scorecard!$D$54:$D$61,SUMPRODUCT(--(Scorecard!$G$54:$G$60<C25))+1),Scorecard!$D$62) -> 0.12630355 | H25: =IF(ISNUMBER(D25),INDEX(Scorecard!$D$63:$D$68,SUMPRODUCT(--(Scorecard!$G$63:$G$67<D25))+1),Scorecard!$D$69) -> -0.34058219 | I25: =IF(ISNUMBER(E25),INDEX(Scorecard!$D$19:$D$26,SUMPRODUCT(--(Scorecard!$G$19:$G$25<E25))+1),Scorecard!$D$27) -> -0.21985597 | J25: =IF(ISNUMBER(F25),INDEX(Scorecard!$D$37:$D$44,SUMPRODUCT(--(Scorecard!$G$37:$G$43<F25))+1),Scorecard!$D$45) -> 0.10218425 | K25: =Inputs!$B$10+Scorecard!$J$5*Loan_Sample!Y5+Scorecard!$J$6*Loan_Sample!Z5+Scorecard!$J$7*I25+Scorecard!$J$8*Loan_Sample!AB5+Scorecard!$J$9*J25+Scorecard!$J$10*Loan_Sample!AD5+Scorecard!$J$11*G25+Scorecard!$J$12*H25 -> -4.8500963 | L25: =MIN(1-Inputs!$B$13,MAX(Inputs!$B$13,1/(1+EXP(-(Inputs!$B$11*K25+Inputs!$B$12))))) -> 0.00691461 | M25: =Loan_Sample!AH5*Inputs!$B$4*B25 -> 567.27122 | N25: =L25*Inputs!$B$4*B25 -> 567.27122 | O25: =Inputs!$B$37+Inputs!$B$38*MAX(Loan_Sample!H5-Inputs!$C$38,0)+Inputs!$B$39*MAX(Loan_Sample!H5-Inputs!$C$39,0)+Inputs!$B$40*MAX(Loan_Sample!H5-Inputs!$C$40,0)+Inputs!$B$41*MAX(Loan_Sample!H5-Inputs!$C$41,0)+Inputs!$B$42*Inputs!$B$14+Inputs!$B$43*MIN(Loan_Sample!I5/Inputs!$B$17,1)+Inputs!$B$44*MIN(Loan_Sample!E5,Inputs!$B$18)+Inputs!$B$45*Loan_Sample!C5 -> -5.657292 | P25: =MIN(1-Inputs!$B$13,MAX(Inputs!$B$13,1/(1+EXP(-(Inputs!$B$15*O25+Inputs!$B$16))))) -> 0.0024502759 | Q25: =Inputs!$B$37+Inputs!$B$38*MAX(F25-Inputs!$C$38,0)+Inputs!$B$39*MAX(F25-Inputs!$C$39,0)+Inputs!$B$40*MAX(F25-Inputs!$C$40,0)+Inputs!$B$41*MAX(F25-Inputs!$C$41,0)+Inputs!$B$42*Inputs!$B$14+Inputs!$B$43*MIN(Loan_Sample!I5/Inputs!$B$17,1)+Inputs!$B$44*MIN(E25,Inputs!$B$18)+Inputs!$B$45*Loan_Sample!C5 -> -5.657292 | R25: =MIN(1-Inputs!$B$13,MAX(Inputs!$B$13,1/(1+EXP(-(Inputs!$B$15*Q25+Inputs!$B$16))))) -> 0.0024502759
A26: =Loan_Sample!A6 -> 60 | B26: =Loan_Sample!U6 -> 332319.2 | C26: =Loan_Sample!K6+Inputs!$B$26 -> 8.9333334 | D26: =Loan_Sample!L6+Inputs!$B$26 -> 5.071795 | E26: =Loan_Sample!E6/(1+Inputs!$B$25/100) -> 82.01059 | F26: =Loan_Sample!H6-Inputs!$B$24/100 -> 1.1696665 | G26: =IF(ISNUMBER(C26),INDEX(Scorecard!$D$54:$D$61,SUMPRODUCT(--(Scorecard!$G$54:$G$60<C26))+1),Scorecard!$D$62) -> -0.54191718 | H26: =IF(ISNUMBER(D26),INDEX(Scorecard!$D$63:$D$68,SUMPRODUCT(--(Scorecard!$G$63:$G$67<D26))+1),Scorecard!$D$69) -> 0.32248451 | I26: =IF(ISNUMBER(E26),INDEX(Scorecard!$D$19:$D$26,SUMPRODUCT(--(Scorecard!$G$19:$G$25<E26))+1),Scorecard!$D$27) -> -0.034157851 | J26: =IF(ISNUMBER(F26),INDEX(Scorecard!$D$37:$D$44,SUMPRODUCT(--(Scorecard!$G$37:$G$43<F26))+1),Scorecard!$D$45) -> -0.97550357 | K26: =Inputs!$B$10+Scorecard!$J$5*Loan_Sample!Y6+Scorecard!$J$6*Loan_Sample!Z6+Scorecard!$J$7*I26+Scorecard!$J$8*Loan_Sample!AB6+Scorecard!$J$9*J26+Scorecard!$J$10*Loan_Sample!AD6+Scorecard!$J$11*G26+Scorecard!$J$12*H26 -> -3.3245062 | L26: =MIN(1-Inputs!$B$13,MAX(Inputs!$B$13,1/(1+EXP(-(Inputs!$B$11*K26+Inputs!$B$12))))) -> 0.034200854 | M26: =Loan_Sample!AH6*Inputs!$B$4*B26 -> 3977.9601 | N26: =L26*Inputs!$B$4*B26 -> 3977.9601 | O26: =Inputs!$B$37+Inputs!$B$38*MAX(Loan_Sample!H6-Inputs!$C$38,0)+Inputs!$B$39*MAX(Loan_Sample!H6-Inputs!$C$39,0)+Inputs!$B$40*MAX(Loan_Sample!H6-Inputs!$C$40,0)+Inputs!$B$41*MAX(Loan_Sample!H6-Inputs!$C$41,0)+Inputs!$B$42*Inputs!$B$14+Inputs!$B$43*MIN(Loan_Sample!I6/Inputs!$B$17,1)+Inputs!$B$44*MIN(Loan_Sample!E6,Inputs!$B$18)+Inputs!$B$45*Loan_Sample!C6 -> -3.5596376 | P26: =MIN(1-Inputs!$B$13,MAX(Inputs!$B$13,1/(1+EXP(-(Inputs!$B$15*O26+Inputs!$B$16))))) -> 0.02597023 | Q26: =Inputs!$B$37+Inputs!$B$38*MAX(F26-Inputs!$C$38,0)+Inputs!$B$39*MAX(F26-Inputs!$C$39,0)+Inputs!$B$40*MAX(F26-Inputs!$C$40,0)+Inputs!$B$41*MAX(F26-Inputs!$C$41,0)+Inputs!$B$42*Inputs!$B$14+Inputs!$B$43*MIN(Loan_Sample!I6/Inputs!$B$17,1)+Inputs!$B$44*MIN(E26,Inputs!$B$18)+Inputs!$B$45*Loan_Sample!C6 -> -3.5596376 | R26: =MIN(1-Inputs!$B$13,MAX(Inputs!$B$13,1/(1+EXP(-(Inputs!$B$15*Q26+Inputs!$B$16))))) -> 0.02597023
A27: =Loan_Sample!A7 -> 90 | B27: =Loan_Sample!U7 -> 126916.92 | C27: =Loan_Sample!K7+Inputs!$B$26 -> 4.1583333 | D27: =Loan_Sample!L7+Inputs!$B$26 -> -1.875 | E27: =Loan_Sample!E7/(1+Inputs!$B$25/100) -> 46.712036 | F27: =Loan_Sample!H7-Inputs!$B$24/100 -> 1.2183335 | G27: =IF(ISNUMBER(C27),INDEX(Scorecard!$D$54:$D$61,SUMPRODUCT(--(Scorecard!$G$54:$G$60<C27))+1),Scorecard!$D$62) -> 0.4890505 | H27: =IF(ISNUMBER(D27),INDEX(Scorecard!$D$63:$D$68,SUMPRODUCT(--(Scorecard!$G$63:$G$67<D27))+1),Scorecard!$D$69) -> -0.34058219 | I27: =IF(ISNUMBER(E27),INDEX(Scorecard!$D$19:$D$26,SUMPRODUCT(--(Scorecard!$G$19:$G$25<E27))+1),Scorecard!$D$27) -> 0.57899015 | J27: =IF(ISNUMBER(F27),INDEX(Scorecard!$D$37:$D$44,SUMPRODUCT(--(Scorecard!$G$37:$G$43<F27))+1),Scorecard!$D$45) -> -0.97550357 | K27: =Inputs!$B$10+Scorecard!$J$5*Loan_Sample!Y7+Scorecard!$J$6*Loan_Sample!Z7+Scorecard!$J$7*I27+Scorecard!$J$8*Loan_Sample!AB7+Scorecard!$J$9*J27+Scorecard!$J$10*Loan_Sample!AD7+Scorecard!$J$11*G27+Scorecard!$J$12*H27 -> -3.9895295 | L27: =MIN(1-Inputs!$B$13,MAX(Inputs!$B$13,1/(1+EXP(-(Inputs!$B$11*K27+Inputs!$B$12))))) -> 0.017128991 | M27: =Loan_Sample!AH7*Inputs!$B$4*B27 -> 760.88558 | N27: =L27*Inputs!$B$4*B27 -> 760.88558 | O27: =Inputs!$B$37+Inputs!$B$38*MAX(Loan_Sample!H7-Inputs!$C$38,0)+Inputs!$B$39*MAX(Loan_Sample!H7-Inputs!$C$39,0)+Inputs!$B$40*MAX(Loan_Sample!H7-Inputs!$C$40,0)+Inputs!$B$41*MAX(Loan_Sample!H7-Inputs!$C$41,0)+Inputs!$B$42*Inputs!$B$14+Inputs!$B$43*MIN(Loan_Sample!I7/Inputs!$B$17,1)+Inputs!$B$44*MIN(Loan_Sample!E7,Inputs!$B$18)+Inputs!$B$45*Loan_Sample!C7 -> -3.4162231 | P27: =MIN(1-Inputs!$B$13,MAX(Inputs!$B$13,1/(1+EXP(-(Inputs!$B$15*O27+Inputs!$B$16))))) -> 0.030429002 | Q27: =Inputs!$B$37+Inputs!$B$38*MAX(F27-Inputs!$C$38,0)+Inputs!$B$39*MAX(F27-Inputs!$C$39,0)+Inputs!$B$40*MAX(F27-Inputs!$C$40,0)+Inputs!$B$41*MAX(F27-Inputs!$C$41,0)+Inputs!$B$42*Inputs!$B$14+Inputs!$B$43*MIN(Loan_Sample!I7/Inputs!$B$17,1)+Inputs!$B$44*MIN(E27,Inputs!$B$18)+Inputs!$B$45*Loan_Sample!C7 -> -3.4162231 | R27: =MIN(1-Inputs!$B$13,MAX(Inputs!$B$13,1/(1+EXP(-(Inputs!$B$15*Q27+Inputs!$B$16))))) -> 0.030429002
A28: =Loan_Sample!A8 -> 234 | B28: =Loan_Sample!U8 -> 150848.31 | C28: =Loan_Sample!K8+Inputs!$B$26 -> 4.4583335 | D28: =Loan_Sample!L8+Inputs!$B$26 -> -1.875 | E28: =Loan_Sample!E8/(1+Inputs!$B$25/100) -> 77.960373 | F28: =Loan_Sample!H8-Inputs!$B$24/100 -> -0.43866658 | G28: =IF(ISNUMBER(C28),INDEX(Scorecard!$D$54:$D$61,SUMPRODUCT(--(Scorecard!$G$54:$G$60<C28))+1),Scorecard!$D$62) -> 0.409483 | H28: =IF(ISNUMBER(D28),INDEX(Scorecard!$D$63:$D$68,SUMPRODUCT(--(Scorecard!$G$63:$G$67<D28))+1),Scorecard!$D$69) -> -0.34058219 | I28: =IF(ISNUMBER(E28),INDEX(Scorecard!$D$19:$D$26,SUMPRODUCT(--(Scorecard!$G$19:$G$25<E28))+1),Scorecard!$D$27) -> -0.034157851 | J28: =IF(ISNUMBER(F28),INDEX(Scorecard!$D$37:$D$44,SUMPRODUCT(--(Scorecard!$G$37:$G$43<F28))+1),Scorecard!$D$45) -> 0.76971683 | K28: =Inputs!$B$10+Scorecard!$J$5*Loan_Sample!Y8+Scorecard!$J$6*Loan_Sample!Z8+Scorecard!$J$7*I28+Scorecard!$J$8*Loan_Sample!AB8+Scorecard!$J$9*J28+Scorecard!$J$10*Loan_Sample!AD8+Scorecard!$J$11*G28+Scorecard!$J$12*H28 -> -5.8231985 | L28: =MIN(1-Inputs!$B$13,MAX(Inputs!$B$13,1/(1+EXP(-(Inputs!$B$11*K28+Inputs!$B$12))))) -> 0.002461225 | M28: =Loan_Sample!AH8*Inputs!$B$4*B28 -> 129.94507 | N28: =L28*Inputs!$B$4*B28 -> 129.94507 | O28: =Inputs!$B$37+Inputs!$B$38*MAX(Loan_Sample!H8-Inputs!$C$38,0)+Inputs!$B$39*MAX(Loan_Sample!H8-Inputs!$C$39,0)+Inputs!$B$40*MAX(Loan_Sample!H8-Inputs!$C$40,0)+Inputs!$B$41*MAX(Loan_Sample!H8-Inputs!$C$41,0)+Inputs!$B$42*Inputs!$B$14+Inputs!$B$43*MIN(Loan_Sample!I8/Inputs!$B$17,1)+Inputs!$B$44*MIN(Loan_Sample!E8,Inputs!$B$18)+Inputs!$B$45*Loan_Sample!C8 -> -6.1222804 | P28: =MIN(1-Inputs!$B$13,MAX(Inputs!$B$13,1/(1+EXP(-(Inputs!$B$15*O28+Inputs!$B$16))))) -> 0.0014457222 | Q28: =Inputs!$B$37+Inputs!$B$38*MAX(F28-Inputs!$C$38,0)+Inputs!$B$39*MAX(F28-Inputs!$C$39,0)+Inputs!$B$40*MAX(F28-Inputs!$C$40,0)+Inputs!$B$41*MAX(F28-Inputs!$C$41,0)+Inputs!$B$42*Inputs!$B$14+Inputs!$B$43*MIN(Loan_Sample!I8/Inputs!$B$17,1)+Inputs!$B$44*MIN(E28,Inputs!$B$18)+Inputs!$B$45*Loan_Sample!C8 -> -6.1222804 | R28: =MIN(1-Inputs!$B$13,MAX(Inputs!$B$13,1/(1+EXP(-(Inputs!$B$15*Q28+Inputs!$B$16))))) -> 0.0014457222
A29: =Loan_Sample!A9 -> 268 | B29: =Loan_Sample!U9 -> 156562.62 | C29: =Loan_Sample!K9+Inputs!$B$26 -> 9.6333332 | D29: =Loan_Sample!L9+Inputs!$B$26 -> 5.0717945 | E29: =Loan_Sample!E9/(1+Inputs!$B$25/100) -> 79.192024 | F29: =Loan_Sample!H9-Inputs!$B$24/100 -> 0.81566644 | G29: =IF(ISNUMBER(C29),INDEX(Scorecard!$D$54:$D$61,SUMPRODUCT(--(Scorecard!$G$54:$G$60<C29))+1),Scorecard!$D$62) -> -0.54191718 | H29: =IF(ISNUMBER(D29),INDEX(Scorecard!$D$63:$D$68,SUMPRODUCT(--(Scorecard!$G$63:$G$67<D29))+1),Scorecard!$D$69) -> 0.32248451 | I29: =IF(ISNUMBER(E29),INDEX(Scorecard!$D$19:$D$26,SUMPRODUCT(--(Scorecard!$G$19:$G$25<E29))+1),Scorecard!$D$27) -> -0.034157851 | J29: =IF(ISNUMBER(F29),INDEX(Scorecard!$D$37:$D$44,SUMPRODUCT(--(Scorecard!$G$37:$G$43<F29))+1),Scorecard!$D$45) -> -0.56945472 | K29: =Inputs!$B$10+Scorecard!$J$5*Loan_Sample!Y9+Scorecard!$J$6*Loan_Sample!Z9+Scorecard!$J$7*I29+Scorecard!$J$8*Loan_Sample!AB9+Scorecard!$J$9*J29+Scorecard!$J$10*Loan_Sample!AD9+Scorecard!$J$11*G29+Scorecard!$J$12*H29 -> -2.9764854 | L29: =MIN(1-Inputs!$B$13,MAX(Inputs!$B$13,1/(1+EXP(-(Inputs!$B$11*K29+Inputs!$B$12))))) -> 0.048815021 | M29: =Loan_Sample!AH9*Inputs!$B$4*B29 -> 2674.9127 | N29: =L29*Inputs!$B$4*B29 -> 2674.9127 | O29: =Inputs!$B$37+Inputs!$B$38*MAX(Loan_Sample!H9-Inputs!$C$38,0)+Inputs!$B$39*MAX(Loan_Sample!H9-Inputs!$C$39,0)+Inputs!$B$40*MAX(Loan_Sample!H9-Inputs!$C$40,0)+Inputs!$B$41*MAX(Loan_Sample!H9-Inputs!$C$41,0)+Inputs!$B$42*Inputs!$B$14+Inputs!$B$43*MIN(Loan_Sample!I9/Inputs!$B$17,1)+Inputs!$B$44*MIN(Loan_Sample!E9,Inputs!$B$18)+Inputs!$B$45*Loan_Sample!C9 -> -4.2531815 | P29: =MIN(1-Inputs!$B$13,MAX(Inputs!$B$13,1/(1+EXP(-(Inputs!$B$15*O29+Inputs!$B$16))))) -> 0.011974719 | Q29: =Inputs!$B$37+Inputs!$B$38*MAX(F29-Inputs!$C$38,0)+Inputs!$B$39*MAX(F29-Inputs!$C$39,0)+Inputs!$B$40*MAX(F29-Inputs!$C$40,0)+Inputs!$B$41*MAX(F29-Inputs!$C$41,0)+Inputs!$B$42*Inputs!$B$14+Inputs!$B$43*MIN(Loan_Sample!I9/Inputs!$B$17,1)+Inputs!$B$44*MIN(E29,Inputs!$B$18)+Inputs!$B$45*Loan_Sample!C9 -> -4.2531815 | R29: =MIN(1-Inputs!$B$13,MAX(Inputs!$B$13,1/(1+EXP(-(Inputs!$B$15*Q29+Inputs!$B$16))))) -> 0.011974719
A30: =Loan_Sample!A10 -> 273 | B30: =Loan_Sample!U10 -> 204130.56 | C30: =Loan_Sample!K10+Inputs!$B$26 -> 4.4000001 | D30: =Loan_Sample!L10+Inputs!$B$26 -> -0.20833302 | E30: =Loan_Sample!E10/(1+Inputs!$B$25/100) -> 64.415588 | F30: =Loan_Sample!H10-Inputs!$B$24/100 -> -2.9843333 | G30: =IF(ISNUMBER(C30),INDEX(Scorecard!$D$54:$D$61,SUMPRODUCT(--(Scorecard!$G$54:$G$60<C30))+1),Scorecard!$D$62) -> 0.4890505 | H30: =IF(ISNUMBER(D30),INDEX(Scorecard!$D$63:$D$68,SUMPRODUCT(--(Scorecard!$G$63:$G$67<D30))+1),Scorecard!$D$69) -> 0.32248451 | I30: =IF(ISNUMBER(E30),INDEX(Scorecard!$D$19:$D$26,SUMPRODUCT(--(Scorecard!$G$19:$G$25<E30))+1),Scorecard!$D$27) -> 0.23362161 | J30: =IF(ISNUMBER(F30),INDEX(Scorecard!$D$37:$D$44,SUMPRODUCT(--(Scorecard!$G$37:$G$43<F30))+1),Scorecard!$D$45) -> 1.3505764 | K30: =Inputs!$B$10+Scorecard!$J$5*Loan_Sample!Y10+Scorecard!$J$6*Loan_Sample!Z10+Scorecard!$J$7*I30+Scorecard!$J$8*Loan_Sample!AB10+Scorecard!$J$9*J30+Scorecard!$J$10*Loan_Sample!AD10+Scorecard!$J$11*G30+Scorecard!$J$12*H30 -> -2.8171338 | L30: =MIN(1-Inputs!$B$13,MAX(Inputs!$B$13,1/(1+EXP(-(Inputs!$B$11*K30+Inputs!$B$12))))) -> 0.057336 | M30: =Loan_Sample!AH10*Inputs!$B$4*B30 -> 4096.4105 | N30: =L30*Inputs!$B$4*B30 -> 4096.4105 | O30: =Inputs!$B$37+Inputs!$B$38*MAX(Loan_Sample!H10-Inputs!$C$38,0)+Inputs!$B$39*MAX(Loan_Sample!H10-Inputs!$C$39,0)+Inputs!$B$40*MAX(Loan_Sample!H10-Inputs!$C$40,0)+Inputs!$B$41*MAX(Loan_Sample!H10-Inputs!$C$41,0)+Inputs!$B$42*Inputs!$B$14+Inputs!$B$43*MIN(Loan_Sample!I10/Inputs!$B$17,1)+Inputs!$B$44*MIN(Loan_Sample!E10,Inputs!$B$18)+Inputs!$B$45*Loan_Sample!C10 -> -5.8852016 | P30: =MIN(1-Inputs!$B$13,MAX(Inputs!$B$13,1/(1+EXP(-(Inputs!$B$15*O30+Inputs!$B$16))))) -> 0.0018920723 | Q30: =Inputs!$B$37+Inputs!$B$38*MAX(F30-Inputs!$C$38,0)+Inputs!$B$39*MAX(F30-Inputs!$C$39,0)+Inputs!$B$40*MAX(F30-Inputs!$C$40,0)+Inputs!$B$41*MAX(F30-Inputs!$C$41,0)+Inputs!$B$42*Inputs!$B$14+Inputs!$B$43*MIN(Loan_Sample!I10/Inputs!$B$17,1)+Inputs!$B$44*MIN(E30,Inputs!$B$18)+Inputs!$B$45*Loan_Sample!C10 -> -5.8852016 | R30: =MIN(1-Inputs!$B$13,MAX(Inputs!$B$13,1/(1+EXP(-(Inputs!$B$15*Q30+Inputs!$B$16))))) -> 0.0018920723
A31: =Loan_Sample!A11 -> 304 | B31: =Loan_Sample!U11 -> 197501.1 | C31: =Loan_Sample!K11+Inputs!$B$26 -> 3.7 | D31: =Loan_Sample!L11+Inputs!$B$26 -> -0.20833325 | E31: =Loan_Sample!E11/(1+Inputs!$B$25/100) -> 44.414982 | F31: =Loan_Sample!H11-Inputs!$B$24/100 -> -2.7733333 | G31: =IF(ISNUMBER(C31),INDEX(Scorecard!$D$54:$D$61,SUMPRODUCT(--(Scorecard!$G$54:$G$60<C31))+1),Scorecard!$D$62) -> 0.4890505 | H31: =IF(ISNUMBER(D31),INDEX(Scorecard!$D$63:$D$68,SUMPRODUCT(--(Scorecard!$G$63:$G$67<D31))+1),Scorecard!$D$69) -> 0.32248451 | I31: =IF(ISNUMBER(E31),INDEX(Scorecard!$D$19:$D$26,SUMPRODUCT(--(Scorecard!$G$19:$G$25<E31))+1),Scorecard!$D$27) -> 0.57899015 | J31: =IF(ISNUMBER(F31),INDEX(Scorecard!$D$37:$D$44,SUMPRODUCT(--(Scorecard!$G$37:$G$43<F31))+1),Scorecard!$D$45) -> 1.3505764 | K31: =Inputs!$B$10+Scorecard!$J$5*Loan_Sample!Y11+Scorecard!$J$6*Loan_Sample!Z11+Scorecard!$J$7*I31+Scorecard!$J$8*Loan_Sample!AB11+Scorecard!$J$9*J31+Scorecard!$J$10*Loan_Sample!AD11+Scorecard!$J$11*G31+Scorecard!$J$12*H31 -> -5.4589768 | L31: =MIN(1-Inputs!$B$13,MAX(Inputs!$B$13,1/(1+EXP(-(Inputs!$B$11*K31+Inputs!$B$12))))) -> 0.0036248001 | M31: =Loan_Sample!AH11*Inputs!$B$4*B31 -> 250.56571 | N31: =L31*Inputs!$B$4*B31 -> 250.56571 | O31: =Inputs!$B$37+Inputs!$B$38*MAX(Loan_Sample!H11-Inputs!$C$38,0)+Inputs!$B$39*MAX(Loan_Sample!H11-Inputs!$C$39,0)+Inputs!$B$40*MAX(Loan_Sample!H11-Inputs!$C$40,0)+Inputs!$B$41*MAX(Loan_Sample!H11-Inputs!$C$41,0)+Inputs!$B$42*Inputs!$B$14+Inputs!$B$43*MIN(Loan_Sample!I11/Inputs!$B$17,1)+Inputs!$B$44*MIN(Loan_Sample!E11,Inputs!$B$18)+Inputs!$B$45*Loan_Sample!C11 -> -5.4904446 | P31: =MIN(1-Inputs!$B$13,MAX(Inputs!$B$13,1/(1+EXP(-(Inputs!$B$15*O31+Inputs!$B$16))))) -> 0.002960508 | Q31: =Inputs!$B$37+Inputs!$B$38*MAX(F31-Inputs!$C$38,0)+Inputs!$B$39*MAX(F31-Inputs!$C$39,0)+Inputs!$B$40*MAX(F31-Inputs!$C$40,0)+Inputs!$B$41*MAX(F31-Inputs!$C$41,0)+Inputs!$B$42*Inputs!$B$14+Inputs!$B$43*MIN(Loan_Sample!I11/Inputs!$B$17,1)+Inputs!$B$44*MIN(E31,Inputs!$B$18)+Inputs!$B$45*Loan_Sample!C11 -> -5.4904446 | R31: =MIN(1-Inputs!$B$13,MAX(Inputs!$B$13,1/(1+EXP(-(Inputs!$B$15*Q31+Inputs!$B$16))))) -> 0.002960508
A32: =Loan_Sample!A12 -> 337 | B32: =Loan_Sample!U12 -> 133080.64 | C32: =Loan_Sample!K12+Inputs!$B$26 -> 5.1999998 | D32: =Loan_Sample!L12+Inputs!$B$26 -> -0.45833349 | E32: =Loan_Sample!E12/(1+Inputs!$B$25/100) -> 50.710003 | F32: =Loan_Sample!H12-Inputs!$B$24/100 -> -2.8173335 | G32: =IF(ISNUMBER(C32),INDEX(Scorecard!$D$54:$D$61,SUMPRODUCT(--(Scorecard!$G$54:$G$60<C32))+1),Scorecard!$D$62) -> 0.21442935 | H32: =IF(ISNUMBER(D32),INDEX(Scorecard!$D$63:$D$68,SUMPRODUCT(--(Scorecard!$G$63:$G$67<D32))+1),Scorecard!$D$69) -> 0.32248451 | I32: =IF(ISNUMBER(E32),INDEX(Scorecard!$D$19:$D$26,SUMPRODUCT(--(Scorecard!$G$19:$G$25<E32))+1),Scorecard!$D$27) -> 0.57899015 | J32: =IF(ISNUMBER(F32),INDEX(Scorecard!$D$37:$D$44,SUMPRODUCT(--(Scorecard!$G$37:$G$43<F32))+1),Scorecard!$D$45) -> 1.3505764 | K32: =Inputs!$B$10+Scorecard!$J$5*Loan_Sample!Y12+Scorecard!$J$6*Loan_Sample!Z12+Scorecard!$J$7*I32+Scorecard!$J$8*Loan_Sample!AB12+Scorecard!$J$9*J32+Scorecard!$J$10*Loan_Sample!AD12+Scorecard!$J$11*G32+Scorecard!$J$12*H32 -> -6.7372628 | L32: =MIN(1-Inputs!$B$13,MAX(Inputs!$B$13,1/(1+EXP(-(Inputs!$B$11*K32+Inputs!$B$12))))) -> 0.00093023591 | M32: =Loan_Sample!AH12*Inputs!$B$4*B32 -> 43.328737 | N32: =L32*Inputs!$B$4*B32 -> 43.328737 | O32: =Inputs!$B$37+Inputs!$B$38*MAX(Loan_Sample!H12-Inputs!$C$38,0)+Inputs!$B$39*MAX(Loan_Sample!H12-Inputs!$C$39,0)+Inputs!$B$40*MAX(Loan_Sample!H12-Inputs!$C$40,0)+Inputs!$B$41*MAX(Loan_Sample!H12-Inputs!$C$41,0)+Inputs!$B$42*Inputs!$B$14+Inputs!$B$43*MIN(Loan_Sample!I12/Inputs!$B$17,1)+Inputs!$B$44*MIN(Loan_Sample!E12,Inputs!$B$18)+Inputs!$B$45*Loan_Sample!C12 -> -5.2911926 | P32: =MIN(1-Inputs!$B$13,MAX(Inputs!$B$13,1/(1+EXP(-(Inputs!$B$15*O32+Inputs!$B$16))))) -> 0.0037103191 | Q32: =Inputs!$B$37+Inputs!$B$38*MAX(F32-Inputs!$C$38,0)+Inputs!$B$39*MAX(F32-Inputs!$C$39,0)+Inputs!$B$40*MAX(F32-Inputs!$C$40,0)+Inputs!$B$41*MAX(F32-Inputs!$C$41,0)+Inputs!$B$42*Inputs!$B$14+Inputs!$B$43*MIN(Loan_Sample!I12/Inputs!$B$17,1)+Inputs!$B$44*MIN(E32,Inputs!$B$18)+Inputs!$B$45*Loan_Sample!C12 -> -5.2911926 | R32: =MIN(1-Inputs!$B$13,MAX(Inputs!$B$13,1/(1+EXP(-(Inputs!$B$15*Q32+Inputs!$B$16))))) -> 0.0037103191
A33: =Loan_Sample!A13 -> 365 | B33: =Loan_Sample!U13 -> 52936.7 | C33: =Loan_Sample!K13+Inputs!$B$26 -> 5.0083332 | D33: =Loan_Sample!L13+Inputs!$B$26 -> -1.125 | E33: =Loan_Sample!E13/(1+Inputs!$B$25/100) -> 72.61911 | F33: =Loan_Sample!H13-Inputs!$B$24/100 -> -2.0313332 | G33: =IF(ISNUMBER(C33),INDEX(Scorecard!$D$54:$D$61,SUMPRODUCT(--(Scorecard!$G$54:$G$60<C33))+1),Scorecard!$D$62) -> 0.21442935 | H33: =IF(ISNUMBER(D33),INDEX(Scorecard!$D$63:$D$68,SUMPRODUCT(--(Scorecard!$G$63:$G$67<D33))+1),Scorecard!$D$69) -> -0.34058219 | I33: =IF(ISNUMBER(E33),INDEX(Scorecard!$D$19:$D$26,SUMPRODUCT(--(Scorecard!$G$19:$G$25<E33))+1),Scorecard!$D$27) -> -0.034157851 | J33: =IF(ISNUMBER(F33),INDEX(Scorecard!$D$37:$D$44,SUMPRODUCT(--(Scorecard!$G$37:$G$43<F33))+1),Scorecard!$D$45) -> 1.3505764 | K33: =Inputs!$B$10+Scorecard!$J$5*Loan_Sample!Y13+Scorecard!$J$6*Loan_Sample!Z13+Scorecard!$J$7*I33+Scorecard!$J$8*Loan_Sample!AB13+Scorecard!$J$9*J33+Scorecard!$J$10*Loan_Sample!AD13+Scorecard!$J$11*G33+Scorecard!$J$12*H33 -> -3.9164867 | L33: =MIN(1-Inputs!$B$13,MAX(Inputs!$B$13,1/(1+EXP(-(Inputs!$B$11*K33+Inputs!$B$12))))) -> 0.018490539 | M33: =Loan_Sample!AH13*Inputs!$B$4*B33 -> 342.58985 | N33: =L33*Inputs!$B$4*B33 -> 342.58985 | O33: =Inputs!$B$37+Inputs!$B$38*MAX(Loan_Sample!H13-Inputs!$C$38,0)+Inputs!$B$39*MAX(Loan_Sample!H13-Inputs!$C$39,0)+Inputs!$B$40*MAX(Loan_Sample!H13-Inputs!$C$40,0)+Inputs!$B$41*MAX(Loan_Sample!H13-Inputs!$C$41,0)+Inputs!$B$42*Inputs!$B$14+Inputs!$B$43*MIN(Loan_Sample!I13/Inputs!$B$17,1)+Inputs!$B$44*MIN(Loan_Sample!E13,Inputs!$B$18)+Inputs!$B$45*Loan_Sample!C13 -> -5.9156486 | P33: =MIN(1-Inputs!$B$13,MAX(Inputs!$B$13,1/(1+EXP(-(Inputs!$B$15*O33+Inputs!$B$16))))) -> 0.0018278218 | Q33: =Inputs!$B$37+Inputs!$B$38*MAX(F33-Inputs!$C$38,0)+Inputs!$B$39*MAX(F33-Inputs!$C$39,0)+Inputs!$B$40*MAX(F33-Inputs!$C$40,0)+Inputs!$B$41*MAX(F33-Inputs!$C$41,0)+Inputs!$B$42*Inputs!$B$14+Inputs!$B$43*MIN(Loan_Sample!I13/Inputs!$B$17,1)+Inputs!$B$44*MIN(E33,Inputs!$B$18)+Inputs!$B$45*Loan_Sample!C13 -> -5.9156486 | R33: =MIN(1-Inputs!$B$13,MAX(Inputs!$B$13,1/(1+EXP(-(Inputs!$B$15*Q33+Inputs!$B$16))))) -> 0.0018278218
A34: =Loan_Sample!A14 -> 384 | B34: =Loan_Sample!U14 -> 128258.19 | C34: =Loan_Sample!K14+Inputs!$B$26 -> 9.0333338 | D34: =Loan_Sample!L14+Inputs!$B$26 -> 5.0717955 | E34: =Loan_Sample!E14/(1+Inputs!$B$25/100) -> 94.569649 | F34: =Loan_Sample!H14-Inputs!$B$24/100 -> 0.80366683 | G34: =IF(ISNUMBER(C34),INDEX(Scorecard!$D$54:$D$61,SUMPRODUCT(--(Scorecard!$G$54:$G$60<C34))+1),Scorecard!$D$62) -> -0.54191718 | H34: =IF(ISNUMBER(D34),INDEX(Scorecard!$D$63:$D$68,SUMPRODUCT(--(Scorecard!$G$63:$G$67<D34))+1),Scorecard!$D$69) -> 0.32248451 | I34: =IF(ISNUMBER(E34),INDEX(Scorecard!$D$19:$D$26,SUMPRODUCT(--(Scorecard!$G$19:$G$25<E34))+1),Scorecard!$D$27) -> -0.82099237 | J34: =IF(ISNUMBER(F34),INDEX(Scorecard!$D$37:$D$44,SUMPRODUCT(--(Scorecard!$G$37:$G$43<F34))+1),Scorecard!$D$45) -> -0.56945472 | K34: =Inputs!$B$10+Scorecard!$J$5*Loan_Sample!Y14+Scorecard!$J$6*Loan_Sample!Z14+Scorecard!$J$7*I34+Scorecard!$J$8*Loan_Sample!AB14+Scorecard!$J$9*J34+Scorecard!$J$10*Loan_Sample!AD14+Scorecard!$J$11*G34+Scorecard!$J$12*H34 -> -2.5000565 | L34: =MIN(1-Inputs!$B$13,MAX(Inputs!$B$13,1/(1+EXP(-(Inputs!$B$11*K34+Inputs!$B$12))))) -> 0.078584532 | M34: =Loan_Sample!AH14*Inputs!$B$4*B34 -> 3527.6884 | N34: =L34*Inputs!$B$4*B34 -> 3527.6884 | O34: =Inputs!$B$37+Inputs!$B$38*MAX(Loan_Sample!H14-Inputs!$C$38,0)+Inputs!$B$39*MAX(Loan_Sample!H14-Inputs!$C$39,0)+Inputs!$B$40*MAX(Loan_Sample!H14-Inputs!$C$40,0)+Inputs!$B$41*MAX(Loan_Sample!H14-Inputs!$C$41,0)+Inputs!$B$42*Inputs!$B$14+Inputs!$B$43*MIN(Loan_Sample!I14/Inputs!$B$17,1)+Inputs!$B$44*MIN(Loan_Sample!E14,Inputs!$B$18)+Inputs!$B$45*Loan_Sample!C14 -> -4.4209284 | P34: =MIN(1-Inputs!$B$13,MAX(Inputs!$B$13,1/(1+EXP(-(Inputs!$B$15*O34+Inputs!$B$16))))) -> 0.0099163443 | Q34: =Inputs!$B$37+Inputs!$B$38*MAX(F34-Inputs!$C$38,0)+Inputs!$B$39*MAX(F34-Inputs!$C$39,0)+Inputs!$B$40*MAX(F34-Inputs!$C$40,0)+Inputs!$B$41*MAX(F34-Inputs!$C$41,0)+Inputs!$B$42*Inputs!$B$14+Inputs!$B$43*MIN(Loan_Sample!I14/Inputs!$B$17,1)+Inputs!$B$44*MIN(E34,Inputs!$B$18)+Inputs!$B$45*Loan_Sample!C14 -> -4.4209284 | R34: =MIN(1-Inputs!$B$13,MAX(Inputs!$B$13,1/(1+EXP(-(Inputs!$B$15*Q34+Inputs!$B$16))))) -> 0.0099163443
A35: =Loan_Sample!A15 -> 443 | B35: =Loan_Sample!U15 -> 183935 | C35: =Loan_Sample!K15+Inputs!$B$26 -> 3.7 | D35: =Loan_Sample!L15+Inputs!$B$26 -> -0.45833325 | E35: =Loan_Sample!E15/(1+Inputs!$B$25/100) -> 62.999836 | F35: =Loan_Sample!H15-Inputs!$B$24/100 -> -1.9593334 | G35: =IF(ISNUMBER(C35),INDEX(Scorecard!$D$54:$D$61,SUMPRODUCT(--(Scorecard!$G$54:$G$60<C35))+1),Scorecard!$D$62) -> 0.4890505 | H35: =IF(ISNUMBER(D35),INDEX(Scorecard!$D$63:$D$68,SUMPRODUCT(--(Scorecard!$G$63:$G$67<D35))+1),Scorecard!$D$69) -> 0.32248451 | I35: =IF(ISNUMBER(E35),INDEX(Scorecard!$D$19:$D$26,SUMPRODUCT(--(Scorecard!$G$19:$G$25<E35))+1),Scorecard!$D$27) -> 0.23362161 | J35: =IF(ISNUMBER(F35),INDEX(Scorecard!$D$37:$D$44,SUMPRODUCT(--(Scorecard!$G$37:$G$43<F35))+1),Scorecard!$D$45) -> 1.3505764 | K35: =Inputs!$B$10+Scorecard!$J$5*Loan_Sample!Y15+Scorecard!$J$6*Loan_Sample!Z15+Scorecard!$J$7*I35+Scorecard!$J$8*Loan_Sample!AB15+Scorecard!$J$9*J35+Scorecard!$J$10*Loan_Sample!AD15+Scorecard!$J$11*G35+Scorecard!$J$12*H35 -> -5.7411737 | L35: =MIN(1-Inputs!$B$13,MAX(Inputs!$B$13,1/(1+EXP(-(Inputs!$B$11*K35+Inputs!$B$12))))) -> 0.0026855437 | M35: =Loan_Sample!AH15*Inputs!$B$4*B35 -> 172.88792 | N35: =L35*Inputs!$B$4*B35 -> 172.88792 | O35: =Inputs!$B$37+Inputs!$B$38*MAX(Loan_Sample!H15-Inputs!$C$38,0)+Inputs!$B$39*MAX(Loan_Sample!H15-Inputs!$C$39,0)+Inputs!$B$40*MAX(Loan_Sample!H15-Inputs!$C$40,0)+Inputs!$B$41*MAX(Loan_Sample!H15-Inputs!$C$41,0)+Inputs!$B$42*Inputs!$B$14+Inputs!$B$43*MIN(Loan_Sample!I15/Inputs!$B$17,1)+Inputs!$B$44*MIN(Loan_Sample!E15,Inputs!$B$18)+Inputs!$B$45*Loan_Sample!C15 -> -5.4221052 | P35: =MIN(1-Inputs!$B$13,MAX(Inputs!$B$13,1/(1+EXP(-(Inputs!$B$15*O35+Inputs!$B$16))))) -> 0.0031989089 | Q35: =Inputs!$B$37+Inputs!$B$38*MAX(F35-Inputs!$C$38,0)+Inputs!$B$39*MAX(F35-Inputs!$C$39,0)+Inputs!$B$40*MAX(F35-Inputs!$C$40,0)+Inputs!$B$41*MAX(F35-Inputs!$C$41,0)+Inputs!$B$42*Inputs!$B$14+Inputs!$B$43*MIN(Loan_Sample!I15/Inputs!$B$17,1)+Inputs!$B$44*MIN(E35,Inputs!$B$18)+Inputs!$B$45*Loan_Sample!C15 -> -5.4221052 | R35: =MIN(1-Inputs!$B$13,MAX(Inputs!$B$13,1/(1+EXP(-(Inputs!$B$15*Q35+Inputs!$B$16))))) -> 0.0031989089
A36: =Loan_Sample!A16 -> 444 | B36: =Loan_Sample!U16 -> 159668.86 | C36: =Loan_Sample!K16+Inputs!$B$26 -> 4.4230771 | D36: =Loan_Sample!L16+Inputs!$B$26 -> -0.2769227 | E36: =Loan_Sample!E16/(1+Inputs!$B$25/100) -> 56.524651 | F36: =Loan_Sample!H16-Inputs!$B$24/100 -> 0.40266633 | G36: =IF(ISNUMBER(C36),INDEX(Scorecard!$D$54:$D$61,SUMPRODUCT(--(Scorecard!$G$54:$G$60<C36))+1),Scorecard!$D$62) -> 0.409483 | H36: =IF(ISNUMBER(D36),INDEX(Scorecard!$D$63:$D$68,SUMPRODUCT(--(Scorecard!$G$63:$G$67<D36))+1),Scorecard!$D$69) -> 0.32248451 | I36: =IF(ISNUMBER(E36),INDEX(Scorecard!$D$19:$D$26,SUMPRODUCT(--(Scorecard!$G$19:$G$25<E36))+1),Scorecard!$D$27) -> 0.28589934 | J36: =IF(ISNUMBER(F36),INDEX(Scorecard!$D$37:$D$44,SUMPRODUCT(--(Scorecard!$G$37:$G$43<F36))+1),Scorecard!$D$45) -> -0.27122968 | K36: =Inputs!$B$10+Scorecard!$J$5*Loan_Sample!Y16+Scorecard!$J$6*Loan_Sample!Z16+Scorecard!$J$7*I36+Scorecard!$J$8*Loan_Sample!AB16+Scorecard!$J$9*J36+Scorecard!$J$10*Loan_Sample!AD16+Scorecard!$J$11*G36+Scorecard!$J$12*H36 -> -5.2405819 | L36: =MIN(1-Inputs!$B$13,MAX(Inputs!$B$13,1/(1+EXP(-(Inputs!$B$11*K36+Inputs!$B$12))))) -> 0.0045707905 | M36: =Loan_Sample!AH16*Inputs!$B$4*B36 -> 255.43452 | N36: =L36*Inputs!$B$4*B36 -> 255.43452 | O36: =Inputs!$B$37+Inputs!$B$38*MAX(Loan_Sample!H16-Inputs!$C$38,0)+Inputs!$B$39*MAX(Loan_Sample!H16-Inputs!$C$39,0)+Inputs!$B$40*MAX(Loan_Sample!H16-Inputs!$C$40,0)+Inputs!$B$41*MAX(Loan_Sample!H16-Inputs!$C$41,0)+Inputs!$B$42*Inputs!$B$14+Inputs!$B$43*MIN(Loan_Sample!I16/Inputs!$B$17,1)+Inputs!$B$44*MIN(Loan_Sample!E16,Inputs!$B$18)+Inputs!$B$45*Loan_Sample!C16 -> -4.4111069 | P36: =MIN(1-Inputs!$B$13,MAX(Inputs!$B$13,1/(1+EXP(-(Inputs!$B$15*O36+Inputs!$B$16))))) -> 0.010026565 | Q36: =Inputs!$B$37+Inputs!$B$38*MAX(F36-Inputs!$C$38,0)+Inputs!$B$39*MAX(F36-Inputs!$C$39,0)+Inputs!$B$40*MAX(F36-Inputs!$C$40,0)+Inputs!$B$41*MAX(F36-Inputs!$C$41,0)+Inputs!$B$42*Inputs!$B$14+Inputs!$B$43*MIN(Loan_Sample!I16/Inputs!$B$17,1)+Inputs!$B$44*MIN(E36,Inputs!$B$18)+Inputs!$B$45*Loan_Sample!C16 -> -4.4111069 | R36: =MIN(1-Inputs!$B$13,MAX(Inputs!$B$13,1/(1+EXP(-(Inputs!$B$15*Q36+Inputs!$B$16))))) -> 0.010026565
... A2024: =Loan_Sample!A2004 -> 59999 | B2024: =Loan_Sample!U2004 -> 243217.12 | C2024: =Loan_Sample!K2004+Inputs!$B$26 -> 5.4333334 | D2024: =Loan_Sample!L2004+Inputs!$B$26 -> -3.5 | E2024: =Loan_Sample!E2004/(1+Inputs!$B$25/100) -> 66.766762 | F2024: =Loan_Sample!H2004-Inputs!$B$24/100 -> 1.1733334 | G2024: =IF(ISNUMBER(C2024),INDEX(Scorecard!$D$54:$D$61,SUMPRODUCT(--(Scorecard!$G$54:$G$60<C2024))+1),Scorecard!$D$62) -> 0.12630355 | H2024: =IF(ISNUMBER(D2024),INDEX(Scorecard!$D$63:$D$68,SUMPRODUCT(--(Scorecard!$G$63:$G$67<D2024))+1),Scorecard!$D$69) -> -0.34058219 | I2024: =IF(ISNUMBER(E2024),INDEX(Scorecard!$D$19:$D$26,SUMPRODUCT(--(Scorecard!$G$19:$G$25<E2024))+1),Scorecard!$D$27) -> 0.053084309 | J2024: =IF(ISNUMBER(F2024),INDEX(Scorecard!$D$37:$D$44,SUMPRODUCT(--(Scorecard!$G$37:$G$43<F2024))+1),Scorecard!$D$45) -> -0.97550357 | K2024: =Inputs!$B$10+Scorecard!$J$5*Loan_Sample!Y2004+Scorecard!$J$6*Loan_Sample!Z2004+Scorecard!$J$7*I2024+Scorecard!$J$8*Loan_Sample!AB2004+Scorecard!$J$9*J2024+Scorecard!$J$10*Loan_Sample!AD2004+Scorecard!$J$11*G2024+Scorecard!$J$12*H2024 -> -5.0030747 | L2024: =MIN(1-Inputs!$B$13,MAX(Inputs!$B$13,1/(1+EXP(-(Inputs!$B$11*K2024+Inputs!$B$12))))) -> 0.0058801546 | M2024: =Loan_Sample!AH2004*Inputs!$B$4*B2024 -> 500.554 | N2024: =L2024*Inputs!$B$4*B2024 -> 500.554 | O2024: =Inputs!$B$37+Inputs!$B$38*MAX(Loan_Sample!H2004-Inputs!$C$38,0)+Inputs!$B$39*MAX(Loan_Sample!H2004-Inputs!$C$39,0)+Inputs!$B$40*MAX(Loan_Sample!H2004-Inputs!$C$40,0)+Inputs!$B$41*MAX(Loan_Sample!H2004-Inputs!$C$41,0)+Inputs!$B$42*Inputs!$B$14+Inputs!$B$43*MIN(Loan_Sample!I2004/Inputs!$B$17,1)+Inputs!$B$44*MIN(Loan_Sample!E2004,Inputs!$B$18)+Inputs!$B$45*Loan_Sample!C2004 -> -3.2490628 | P2024: =MIN(1-Inputs!$B$13,MAX(Inputs!$B$13,1/(1+EXP(-(Inputs!$B$15*O2024+Inputs!$B$16))))) -> 0.036564423 | Q2024: =Inputs!$B$37+Inputs!$B$38*MAX(F2024-Inputs!$C$38,0)+Inputs!$B$39*MAX(F2024-Inputs!$C$39,0)+Inputs!$B$40*MAX(F2024-Inputs!$C$40,0)+Inputs!$B$41*MAX(F2024-Inputs!$C$41,0)+Inputs!$B$42*Inputs!$B$14+Inputs!$B$43*MIN(Loan_Sample!I2004/Inputs!$B$17,1)+Inputs!$B$44*MIN(E2024,Inputs!$B$18)+Inputs!$B$45*Loan_Sample!C2004 -> -3.2490628 | R2024: =MIN(1-Inputs!$B$13,MAX(Inputs!$B$13,1/(1+EXP(-(Inputs!$B$15*Q2024+Inputs!$B$16))))) -> 0.036564423

Sheet Checks
A1: Integrity checks (1 = pass)
A3: check | B3: value | C3: pass
A4: Loan count equals decile count total | B4: =Deciles!B3-SUM(Deciles!$B$10:$B$19) -> 0 | C4: =IF(ABS(B4)<0.5,1,0) -> 1
A5: Decile counts sum to the sample size | B5: =SUM(Deciles!$B$10:$B$19) -> 2000 | C5: =IF(B5=COUNTA(Loan_Sample!$A$5:$A$2004),1,0) -> 1
A6: Events across deciles equal sample events | B6: =SUM(Deciles!$C$10:$C$19)-SUM(Loan_Sample!$T$5:$T$2004) -> 0 | C6: =IF(ABS(B6)<0.5,1,0) -> 1
A7: All base PD within [0,1] | B7: =MIN(Loan_Sample!$AH$5:$AH$2004) -> 0.00032821972 | C7: =IF(AND(B7>=0,MAX(Loan_Sample!$AH$5:$AH$2004)<=1),1,0) -> 1
A8: All stressed PD within [0,1] | B8: =MIN(Scenario!$L$25:$L$2024) -> 0.00032821972 | C8: =IF(AND(B8>=0,MAX(Scenario!$L$25:$L$2024)<=1),1,0) -> 1
A9: All SMM within [0,1] | B9: =MIN(Scenario!$R$25:$R$2024) -> 0.00091395129 | C9: =IF(AND(B9>=0,MAX(Scenario!$R$25:$R$2024,Scenario!$P$25:$P$2024)<=1),1,0) -> 1
A10: Ranks are a permutation of 1..N | B10: =SUM(Loan_Sample!$AJ$5:$AJ$2004)-Deciles!B3*(Deciles!B3+1)/2 -> 0 | C10: =IF(ABS(B10)<0.5,1,0) -> 1
A11: Expected PSI shares sum to 1 | B11: =SUM(PSI!$D$7:$D$16)-1 -> 0 | C11: =IF(ABS(B11)<0.000001,1,0) -> 1
A12: Actual PSI shares sum to 1 | B12: =SUM(PSI!$E$7:$E$16)-1 -> 0 | C12: =IF(ABS(B12)<0.000000001,1,0) -> 1
A13: Cumulative event capture ends at 1 | B13: =Deciles!F19-1 -> 0 | C13: =IF(ABS(B13)<0.000000001,1,0) -> 1
A14: Expected events equal sum of PD | B14: =Calibration!B18-SUM(Loan_Sample!$AH$5:$AH$2004) -> 0 | C14: =IF(ABS(B14)<0.000001,1,0) -> 1
A15: Live PD matches the exported Python PD (max abs diff) | B15: =SUMPRODUCT(MAX(ABS(Loan_Sample!$AH$5:$AH$2004-Loan_Sample!$V$5:$V$2004))) -> 1.1176597e-08 | C15: =IF(B15<0.000001,1,0) -> 1
A16: Live points match the exported Python points (max abs diff) | B16: =SUMPRODUCT(MAX(ABS(Loan_Sample!$AI$5:$AI$2004-Loan_Sample!$W$5:$W$2004))) -> 3.0502851e-05 | C16: =IF(B16<0.001,1,0) -> 1
A17: Calculator per-variable points sum to total score | B17: =Score_Calc!B19-Score_Calc!B18 -> 0 | C17: =IF(ABS(B17)<0.000001,1,0) -> 1
A19: All checks pass (1 = yes) | B19: =IF(SUM(C4:C17)=COUNT(C4:C17),1,0) -> 1

Sheet Conclusions
A1: Conclusions (static text written by build_workbook.py from the computed numbers; rerun the build to refresh)
A3: All data are synthetic, simulated from a known generating process. These results show the method works, not how real loans behave.
A5: Rank ordering: on 2,000 out-of-time loans the decile KS is 0.397; the decile-trapezoid Gini is 0.479 (approximate, exact AUC is 0.747). The top decile holds 38% of defaults, a lift of 3.8x.
A6: Stability: PSI of the scorecard PD against the training bins is 0.0150, in the stable band (thresholds 0.1 and 0.25). Per-variable CSI is on Python_Ref, not recomputed here.
A7: Calibration: mean predicted PD is 1.677% against an observed rate of 1.950% (expected/observed events 0.86); the model is moderately miscalibrated in aggregate. Brier 0.01861 versus 0.01912 for a constant base-rate forecast. Hosmer-Lemeshow statistic 26.5 on 10 groups; with only 39 events the deciles are noisy.
A9: Scenario results on the sample (scorecard re-binned on shocked attributes; prepay hinge logit with BURNOUT fixed at 36.4 months, solved to match the Python GBM base 12-month prepay; an approximation):
A10: Base: expected 12-month defaults 33.5, UPB-weighted PD 1.694%, expected loss $2,719,361 (0.593% of UPB), SMM 1.0034%, 12-month prepay 11.40%.
A11: Rates +200bp: expected 12-month defaults 32.4, UPB-weighted PD 1.635%, expected loss $2,624,544 (0.572% of UPB), SMM 0.2225%, 12-month prepay 2.64%.
A12: Rates -200bp: expected 12-month defaults 34.0, UPB-weighted PD 1.716%, expected loss $2,755,004 (0.601% of UPB), SMM 2.9749%, 12-month prepay 30.40%.
A13: HPI -20%: expected 12-month defaults 41.0, UPB-weighted PD 2.085%, expected loss $3,347,631 (0.730% of UPB), SMM 0.9585%, 12-month prepay 10.91%.
A14: Unemployment +4pt: expected 12-month defaults 55.6, UPB-weighted PD 2.795%, expected loss $4,487,747 (0.978% of UPB), SMM 1.0034%, 12-month prepay 11.40%.
A15: Adverse combined: expected 12-month defaults 65.5, UPB-weighted PD 3.319%, expected loss $5,328,073 (1.161% of UPB), SMM 0.2122%, 12-month prepay 2.52%.
... A20: The Python comparison is in Checks (live formulas versus exported Python scores) and in outputs/excel_reconciliation.json.

Sheet Python_Ref
A1: Python reference values (static, from the full out-of-time population unless stated)
A3: Deciles, scorecard, full OOT (deciles_pd_pd_logit.csv)
A4: decile | B4: n | C4: events | D4: event_rate | E4: mean_score | F4: cum_events_share | G4: lift | H4: ks_at_decile
A5: 1 | B5: 12340 | C5: 1257 | D5: 0.10186386 | E5: 0.08576315 | F5: 0.43904995 | G5: 4.3903216 | H5: 0.34709926
A6: 2 | B6: 12340 | C6: 491 | D6: 0.039789303 | E6: 0.03075779 | F6: 0.61054838 | G6: 1.7149148 | H6: 0.42029185
A7: 3 | B7: 12340 | C7: 301 | D7: 0.02439222 | E7: 0.01860216 | F7: 0.71568285 | G7: 1.0513021 | H7: 0.42554413
A8: 4 | B8: 12340 | C8: 243 | D8: 0.019692058 | E8: 0.012607254 | F8: 0.80055885 | G8: 0.84872565 | H8: 0.41005675
A9: 5 | B9: 12340 | C9: 191 | D9: 0.01547812 | E9: 0.0089404946 | F9: 0.86727209 | G9: 0.66710535 | H9: 0.37597518
A10: 6 | B10: 12339 | C10: 149 | D10: 0.012075533 | E10: 0.0064334323 | F10: 0.9193154 | G10: 0.5204542 | H10: 0.32688352
A11: 7 | B11: 12339 | C11: 92 | D11: 0.0074560337 | E11: 0.004548491 | F11: 0.95144953 | G11: 0.32135427 | H11: 0.25740977
A12: 8 | B12: 12339 | C12: 65 | D12: 0.0052678499 | E12: 0.0030592419 | F12: 0.97415299 | G12: 0.22704378 | H12: 0.17828135
A13: 9 | B13: 12339 | C13: 44 | D13: 0.0035659292 | E13: 0.0018769678 | F13: 0.98952148 | G13: 0.15369117 | H13: 0.091643739
A14: 10 | B14: 12339 | C14: 30 | D14: 0.0024313153 | E14: 0.00095519046 | F14: 1 | G14: 0.10478944 | H14: 0
A17: PSI expected bins (psi_train_bins.csv); -inf shown as -1 and inf as 2 (PD domain bounds)
A18: bin | B18: lo | C18: hi | D18: train_share
A19: 1 | B19: -1 | C19: 0.0016046033 | D19: 0.10000141
A20: 2 | B20: 0.0016046033 | C20: 0.0027144069 | D20: 0.10000141
A21: 3 | B21: 0.0027144069 | C21: 0.0042681407 | D21: 0.10000846
A22: 4 | B22: 0.0042681407 | C22: 0.006159664 | D22: 0.099987311
A23: 5 | B23: 0.006159664 | C23: 0.0085888519 | D23: 0.10000141
A24: 6 | B24: 0.0085888519 | C24: 0.01205079 | D24: 0.10000141
A25: 7 | B25: 0.01205079 | C25: 0.017188131 | D25: 0.10000846
A26: 8 | B26: 0.017188131 | C26: 0.026642986 | D26: 0.099987311
A27: 9 | B27: 0.026642986 | C27: 0.047691937 | D27: 0.10002256
A28: 10 | B28: 0.047691937 | C28: 2 | D28: 0.099980262
A31: Python PSI and CSI, train vs full OOT (psi_csi.csv)
A32: kind | B32: name | C32: psi | D32: band
A33: score | B33: pd_logit:train_vs_calib | C33: 0.10229339 | D33: moderate
A34: score | B34: pd_logit:train_vs_oot | C34: 0.011827461 | D34: stable
A35: score | B35: pd_xgb:train_vs_calib | C35: 0.079807755 | D35: stable
A36: score | B36: pd_xgb:train_vs_oot | C36: 0.0062463464 | D36: stable
A37: score | B37: pd_lgbm:train_vs_calib | C37: 0.077364532 | D37: stable
A38: score | B38: pd_lgbm:train_vs_oot | C38: 0.0087329512 | D38: stable
A39: csi | B39: fico | C39: 0.0015167061 | D39: stable
A40: csi | B40: orig_ltv | C40: 0.00017240901 | D40: stable
A41: csi | B41: mtm_ltv | C41: 0.1487786 | D41: moderate
A42: csi | B42: dti | C42: 0.0010076725 | D42: stable
A43: csi | B43: orig_rate | C43: 0.67139808 | D43: significant
A44: csi | B44: incentive | C44: 0.83194356 | D44: significant
... A55: csi | B55: state | C55: 0.00064074531 | D55: stable
A58: Python GBM scenario summary (scenario_12m.csv; PD and prepay GBMs, 60-month projection)
A59: scenario | B59: default_12m_pct_upb | C59: prepay_12m_pct_upb | D59: avg_cpr_12m | E59: avg_cdr_12m
A60: Base | B60: 1.0924484 | C60: 11.378502 | D60: 0.11575516 | E60: 0.011631025
A61: Rates +200bp | B61: 1.0924484 | C61: 11.378502 | D61: 0.11575516 | E61: 0.011631025
A62: Rates -200bp | B62: 1.0891617 | C62: 11.403295 | D62: 0.11601117 | E62: 0.011593971
A63: HPI -20% | B63: 1.183553 | C63: 11.328387 | D63: 0.11527671 | E63: 0.01263324
A64: Unemployment +4pt | B64: 1.4536931 | C64: 11.365331 | D64: 0.11578564 | E64: 0.015592775
A65: Adverse combined | B65: 1.5639072 | C65: 11.314887 | D65: 0.115309 | E65: 0.016804873
A68: PD model benchmark (benchmark_pd.csv)
A69: model | B69: train_auc | C69: train_gini | D69: train_ks | E69: train_brier | F69: calib_auc | G69: calib_gini | H69: calib_ks | I69: calib_brier | J69: oot_auc | K69: oot_gini | L69: oot_ks | M69: oot_brier | N69: delong_dauc_vs_logit | O69: delong_p_vs_logit | P69: oot_auc_ci_lo | Q69: oot_auc_ci_hi
A70: pd_logit | B70: 0.81162625 | C70: 0.6232525 | D70: 0.48070056 | E70: 0.018766502 | F70: 0.81647476 | G70: 0.63294953 | H70: 0.49143769 | I70: 0.012410518 | J70: 0.78971606 | K70: 0.57943212 | L70: 0.43809029 | M70: 0.021668844 | N70: 0 | P70: 0.75919935 | Q70: 0.79798556
A71: pd_xgb | B71: 0.84797661 | C71: 0.69595322 | D71: 0.53431697 | E71: 0.017593928 | F71: 0.85141808 | G71: 0.70283615 | H71: 0.54077088 | I71: 0.011603522 | J71: 0.81203555 | K71: 0.62407109 | L71: 0.46860996 | M71: 0.020929091 | N71: 0.022319484 | O71: 2.9214096e-26 | P71: 0.78762219 | Q71: 0.82420415
A72: pd_xgb_weighted_sensitivity | B72: 0.85446951 | C72: 0.70893902 | D72: 0.54327109 | E72: 0.15545394 | F72: 0.85195011 | G72: 0.70390021 | H72: 0.54153169 | I72: 0.11567134 | J72: 0.81308735 | K72: 0.62617471 | L72: 0.46762088 | M72: 0.14058198 | N72: 0.023371291 | O72: 2.0265063e-28 | P72: 0.79386687 | Q72: 0.82879069
A73: pd_lgbm | B73: 0.88468926 | C73: 0.76937851 | D73: 0.60947013 | E73: 0.016759604 | F73: 0.8608769 | G73: 0.72175379 | H73: 0.56814873 | I73: 0.011517411 | J73: 0.80833078 | K73: 0.61666156 | L73: 0.46277155 | M73: 0.020971958 | N73: 0.018614717 | O73: 1.1344246e-16 | P73: 0.7855281 | Q73: 0.82274208

Sheet Curves_Python
A1: Python GBM scenario curves (scenario_curves.csv; static reference, 60 months per scenario)
A3: scenario | B3: month | C3: smm | D3: mdr | E3: cpr | F3: cdr | G3: survival_upb | H3: exp_defaults_upb | I3: exp_prepay_upb
A4: Base | B4: 1 | C4: 0.0099683732 | D4: 0.0011430308 | E4: 0.11327527 | F4: 0.013630467 | G4: 0.98890006 | H4: 3023389.9 | I4: 26336851
A5: Base | B5: 2 | C5: 0.010272793 | D5: 0.0011093566 | E5: 0.1165416 | F5: 0.013231354 | G5: 0.97765569 | H5: 2896000.4 | I5: 26787608
A6: Base | B6: 3 | C6: 0.010529998 | D6: 0.0010721872 | E6: 0.11929272 | F6: 0.012790644 | G6: 0.96632413 | H6: 2761633 | I6: 27093041
A7: Base | B7: 4 | C7: 0.010527203 | D7: 0.001033356 | E7: 0.11926287 | F7: 0.012330037 | G7: 0.95516388 | H7: 2625500.3 | I7: 26719364
A8: Base | B8: 5 | C8: 0.010489461 | D8: 0.0010013856 | E8: 0.11885965 | F8: 0.011950665 | G8: 0.9441989 | H8: 2509827.7 | I8: 26263984
A9: Base | B9: 6 | C9: 0.01048522 | D9: 0.00098290245 | E9: 0.11881433 | F9: 0.011731275 | G9: 0.93338122 | H9: 2430297.2 | I9: 25899980
A10: Base | B10: 7 | C10: 0.010358021 | D10: 0.00094937724 | E10: 0.11745408 | F10: 0.011333228 | G10: 0.92283717 | H10: 2315792.3 | I10: 25242076
A11: Base | B11: 8 | C11: 0.0099886089 | D11: 0.0009298783 | E11: 0.11349273 | F11: 0.011101648 | G11: 0.91277077 | H11: 2238023.1 | I11: 24018143
A12: Base | B12: 9 | C12: 0.0099466117 | D12: 0.00090581465 | E12: 0.11304135 | F12: 0.010815786 | G12: 0.90287433 | H12: 2151896.8 | I12: 23608245
A13: Base | B13: 10 | C13: 0.0099387178 | D13: 0.00087763753 | E13: 0.11295648 | F13: 0.010480962 | G13: 0.8931176 | H13: 2058094.1 | I13: 23286224
A14: Base | B14: 11 | C14: 0.0099294257 | D14: 0.00085665224 | E14: 0.11285658 | F14: 0.010231531 | G14: 0.88349327 | H14: 1983049.7 | I14: 22965768
A15: Base | B15: 12 | C15: 0.0099626929 | D15: 0.00083252634 | E15: 0.11321422 | F15: 0.0099446982 | G15: 0.87396446 | H15: 1902455.8 | I15: 22747392
... A363: Adverse combined | B363: 60 | C363: 0.0096721203 | D363: 0.0011359105 | E363: 0.11008595 | F363: 0.013546089 | G363: 0.50491352 | H363: 1336768.8 | I363: 11369471
